Workbook

Sheet Home
A1: INDUSTRY/SECTOR NAME | B1: COMPANY NAME (TOP 5) | C1: COMPANY NAME (BOTTOM 5)
A2: FMCG | B2: HINDUSTAN UNILEVER LTD | C2: GODFREY PHILLIPS INDIA LTD
B3: ITC LTD | C3: KRBL LTD
B4: NESTLE INDIA LTD | C4: BAJAJ HINDUSTHAN SUGAR LTD
B5: VARUN BEVERAGES LTD | C5: DEVYANI INTERNATIONAL LTD
B6: BRITANNIA INDUSTRIES LTD | C6: RADICO KHAITAN LTD
A7: AUTOMOTIVE | B7: TATA MOTORS | C7: SKF INDIA
B8: MAHINDRA AND MAHINDRA | C8: MINDA CORPORATION
B9: MARUTI SUZUKI INDIA | C9: TENNECO CLEAN AIR INDIA LTD
B10: SAMVARDHANA MOTHERSON INTERNATIONAL | C10: ASAHI INDIA GLASS
B11: HYUNDAI MOTOR INDIA | C11: WHEELS INDIA
A12: ENERGY | B12: RELIANCE INDUSTRIES LTD | C12: PETRONET LNG
B13: INDIAN OIL CORPORATION | C13: PREMIER ENERGY
B14: BHARAT PETROLEUM CORPORATION | C14: JAIPRAKASH POWER VENTURES
B15: ONGC | C15: TRANSRAIL LIGHTING
B16: GAIL | C16: ADANI TOTAL GAS
A17: METALS | B17: HINDALCO INDUSTRIES LTD | C17: GODAWARI POWER AND ISPAT LTD
B18: TATA STEEL LTD | C18: MAHARASHTRA SEAMLESS LTD
B19: JSW STEEL | C19: RATNAMANI METALS AND TUBES
B20: VEDANTA LTD | C20: MUKAND LTD
B21: STEEL AUTHORITY OF INDIA | C21: SARDA ENERGY AND MINERALS
A22: PHARMA | B22: SUN PHARMACEUTICALS INDUSTRIES | C22: ABBOTT INDIA LTD
B23: DR REDDY'S LABORATORIES | C23: GLAND PHARMA LTD
B24: AUROBINDO PHARMA | C24: LAURUS LABS LTD
B25: CIPLA | C25: NATCO PHARMA
B26: ZYDUS LIFESCIENCES | C26: AJANTA PHARMA

Sheet Working Capital Analysis
A1: INDUSTRY | B1: TYPE | C1: FY25 | D1: FY24 | E1: FY23 | F1: FY22 | G1: FY21 | H1: FY20
A2: FMCG | B2: AVERAGE WORKING CAPITAL (ALL 10) | C2: =FMCG!C203 -> 4191.034 | D2: =FMCG!D203 -> 4190.799 | E2: =FMCG!E203 -> 3349.898 | F2: =FMCG!F203 -> 3093.634 | G2: =FMCG!G203 -> 3626.5778 | H2: =FMCG!H203 -> 4340.1678
B3: AVERAGE CCC (ALL 10) | C3: =FMCG!C204 -> 71.469085 | D3: =FMCG!D204 -> 64.868809 | E3: =FMCG!E204 -> 60.684045 | F3: =FMCG!F204 -> 62.081887 | G3: =FMCG!G204 -> 74.422336
B4: TOP 5 AVERAGE WORKING CAPITAL | C4: =FMCG!C206 -> 7647.898 | D4: =FMCG!D206 -> 7893.116 | E4: =FMCG!E206 -> 6279.772 | F4: =FMCG!F206 -> 5194.222 | G4: =FMCG!G206 -> 5576.634
B5: TOP 5 AVERAGE CCC | C5: =FMCG!C207 -> 27.775558 | D5: =FMCG!D207 -> 23.885472 | E5: =FMCG!E207 -> 24.218533 | F5: =FMCG!F207 -> 21.218624 | G5: =FMCG!G207 -> 19.131972
B6: BOTTOM 5 AVERAGE WORKING CAPITAL | C6: =FMCG!C209 -> 734.17 | D6: =FMCG!D209 -> 488.482 | E6: =FMCG!E209 -> 420.024 | F6: =FMCG!F209 -> 993.046 | G6: =FMCG!G209 -> 1189.0075
B7: BOTTOM 5 AVERAGE CCC | C7: =FMCG!C210 -> 115.16261 | D7: =FMCG!D210 -> 105.85215 | E7: =FMCG!E210 -> 97.149556 | F7: =FMCG!F210 -> 102.94515 | G7: 110
A9: AUTOMOTIVE | B9: AVERAGE WORKING CAPITAL (ALL 10) | C9: =Automotive!C203 -> 3609.114 | D9: =Automotive!D203 -> 1831.589 | E9: =Automotive!E203 -> 2323.694 | F9: =Automotive!F203 -> 2794.541 | G9: =Automotive!G203 -> 2491.8533 | H9: =Automotive!H203 -> -586.18889
B10: AVERAGE CCC (ALL 10) | C10: =Automotive!C204 -> 1.2629324 | D10: =Automotive!D204 -> 5.7836735 | E10: =Automotive!E204 -> 9.7131422 | F10: =Automotive!F204 -> 5.3854899 | G10: =Automotive!G204 -> 8.2609065
B11: TOP 5 AVERAGE WORKING CAPITAL | C11: =Automotive!C206 -> 6970.096 | D11: =Automotive!D206 -> 3171.158 | E11: =Automotive!E206 -> 4275.144 | F11: =Automotive!F206 -> 5228.58 | G11: =Automotive!G206 -> 4242.324
B12: TOP 5 AVERAGE CCC | C12: =Automotive!C207 -> -26.476812 | D12: =Automotive!D207 -> -21.090319 | E12: =Automotive!E207 -> -17.166165 | F12: =Automotive!F207 -> -24.519473 | G12: =Automotive!G207 -> -27.361934
B13: BOTTOM 5 AVERAGE WORKING CAPITAL | C13: =FMCG!C209 -> 734.17 | D13: =FMCG!D209 -> 488.482 | E13: =FMCG!E209 -> 420.024 | F13: =FMCG!F209 -> 993.046 | G13: =FMCG!G209 -> 1189.0075
B14: BOTTOM 5 AVERAGE CCC | C14: =FMCG!C210 -> 115.16261 | D14: =FMCG!D210 -> 105.85215 | E14: =FMCG!E210 -> 97.149556 | F14: =FMCG!F210 -> 102.94515 | G14: =FMCG!G210 -> 143.53529
A16: ENERGY | B16: AVERAGE WORKING CAPITAL (ALL 10) | C16: ='Energy '!C203 -> -9489.991 | D16: ='Energy '!D203 -> -5930.83 | E16: ='Energy '!E203 -> -4868.983 | F16: ='Energy '!F203 -> -5931.63 | G16: ='Energy '!G203 -> -6778.857
B17: AVERAGE CCC (ALL 10) | C17: ='Energy '!C204 -> 18.009928 | D17: ='Energy '!D204 -> 15.532443 | E17: ='Energy '!E204 -> 11.499665 | F17: ='Energy '!F204 -> 10.432729 | G17: ='Energy '!G204 -> 16.598564
B18: TOP 5 AVERAGE WORKING CAPITAL | C18: ='Energy '!C206 -> -22325.264 | D18: ='Energy '!D206 -> -13967.818 | E18: ='Energy '!E206 -> -11453.12 | F18: ='Energy '!F206 -> -13019.536 | G18: ='Energy '!G206 -> -14749.556
B19: TOP 5 AVERAGE CCC | C19: ='Energy '!C207 -> 17.054511 | D19: ='Energy '!D207 -> 15.087785 | E19: ='Energy '!E207 -> 8.7607728 | F19: ='Energy '!F207 -> 10.521014 | G19: ='Energy '!G207 -> 17.706232
B20: BOTTOM 5 AVERAGE WORKING CAPITAL | C20: ='Energy '!C209 -> 3345.282 | D20: ='Energy '!D209 -> 2106.158 | E20: ='Energy '!E209 -> 1715.154 | F20: ='Energy '!F209 -> 1156.276 | G20: ='Energy '!G209 -> 1191.842
B21: BOTTOM 5 AVERAGE CCC | C21: ='Energy '!C210 -> 18.965344 | D21: ='Energy '!D210 -> 15.977102 | E21: ='Energy '!E210 -> 14.238557 | F21: ='Energy '!F210 -> 10.344444 | G21: ='Energy '!G210 -> 15.490897
A23: METALS | B23: AVERAGE WORKING CAPITAL (ALL 10) | C23: =Metals!C203 -> 1753.674 | D23: =Metals!D203 -> -2333.545 | E23: =Metals!E203 -> -892.826 | F23: =Metals!F203 -> 3454.786 | G23: =Metals!G203 -> -652.413 | H23: =Metals!H203 -> 1301.473
B24: AVERAGE CCC (ALL 10) | C24: =Metals!C204 -> 107.59372 | D24: =Metals!D204 -> 93.312068 | E24: =Metals!E204 -> 77.459847 | F24: =Metals!F204 -> 77.375496 | G24: =Metals!G204 -> 105.97579
B25: TOP 5 AVERAGE WORKING CAPITAL | C25: =Metals!C206 -> 1466.252 | D25: =Metals!D206 -> -6766.536 | E25: =Metals!E206 -> -3562.392 | F25: =Metals!F206 -> 5605.316 | G25: =Metals!G206 -> -2395.272
B26: TOP 5 AVERAGE CCC | C26: =Metals!C207 -> 80.629786 | D26: =Metals!D207 -> 64.089892 | E26: =Metals!E207 -> 42.401071 | F26: =Metals!F207 -> 43.935988 | G26: =Metals!G207 -> 78.45814
B27: BOTTOM 5 AVERAGE WORKING CAPITAL | C27: =Metals!C209 -> 2041.096 | D27: =Metals!D209 -> 2099.446 | E27: =Metals!E209 -> 1776.74 | F27: =Metals!F209 -> 1304.256 | G27: =Metals!G209 -> 1090.446
B28: BOTTOM 5 AVERAGE CCC | C28: =Metals!C210 -> 134.55765 | D28: =Metals!D210 -> 122.53424 | E28: =Metals!E210 -> 112.51862 | F28: =Metals!F210 -> 110.815 | G28: =Metals!G210 -> 133.49344
A30: PHARMA | B30: AVERAGE WORKING CAPITAL (ALL 10) | C30: =Pharma!C203 -> 10024.572 | D30: =Pharma!D203 -> 8582.798 | E30: =Pharma!E203 -> 7156.472 | F30: =Pharma!F203 -> 6202.134 | G30: =Pharma!G203 -> 5028.111 | H30: =Pharma!H203 -> 4171.386
B31: AVERAGE CCC (ALL 10) | C31: =Pharma!C204 -> 215.58123 | D31: =Pharma!D204 -> 211.61664 | E31: =Pharma!E204 -> 222.13207 | F31: =Pharma!F204 -> 228.8944 | G31: =Pharma!G204 -> 218.80489
B32: TOP 5 AVERAGE WORKING CAPITAL | C32: =Pharma!C206 -> 16940.748 | D32: =Pharma!D206 -> 14813.904 | E32: =Pharma!E206 -> 11706.522 | F32: =Pharma!F206 -> 10006.794 | G32: =Pharma!G206 -> 7874.794
B33: TOP 5 AVERAGE CCC | C33: =Pharma!C207 -> 205.33546 | D33: =Pharma!D207 -> 201.87178 | E33: =Pharma!E207 -> 207.83109 | F33: =Pharma!F207 -> 216.59005 | G33: =Pharma!G207 -> 228.19477
B34: BOTTOM 5 AVERAGE WORKING CAPITAL | C34: =Pharma!C209 -> 3108.396 | D34: =Pharma!D209 -> 2351.692 | E34: =Pharma!E209 -> 2606.422 | F34: =Pharma!F209 -> 2397.474 | G34: =Pharma!G209 -> 2181.428
B35: BOTTOM 5 AVERAGE CCC | C35: =Pharma!C210 -> 225.827 | D35: =Pharma!D210 -> 221.36151 | E35: =Pharma!E210 -> 236.43306 | F35: =Pharma!F210 -> 241.19874 | G35: =Pharma!G210 -> 209.41502

Sheet FMCG
A1: HUL
A2: Figures (In Crores) | C2: FY25 | D2: FY24 | E2: FY23 | F2: FY22 | G2: FY21 | H2: FY20
A3: Net Revenue from Operations | C3: 62288 | D3: 60966 | E3: 59549 | F3: 51548 | G3: 46321 | H3: 39238
A4: COGS | C4: 30578 | D4: 29760 | E4: 31716 | F4: 25735 | G4: 22148 | H4: 18259
A5: Current Assets | C5: 22051 | D5: 21324 | E5: 16998 | F5: 15522 | G5: 14217 | H5: 12321
A6: Inventory | C6: 4415 | D6: 4022 | E6: 4251 | F6: 4096 | G6: 3579 | H6: 2767
A7: Trade Receivables | C7: 3819 | D7: 2997 | E7: 3079 | F7: 2236 | G7: 1758 | H7: 1149
A8: Current Liability | C8: 16537 | D8: 12876 | E8: 12028 | F8: 11280 | G8: 11103 | H8: 9317
A9: Trade Payables | C9: 11315 | D9: 10486 | E9: 9574 | F9: 9068 | G9: 8802 | H9: 7535
A11: ANALYSIS PART
A12: WORKING CAPITAL | B12: CURRENT ASSETS - CURRENT LIABILITY | C12: =C5-C8 -> 5514 | D12: =D5-D8 -> 8448 | E12: =E5-E8 -> 4970 | F12: =F5-F8 -> 4242 | G12: =G5-G8 -> 3114 | H12: =H5-H8 -> 3004
A13: AVERAGE INVENTORY | B13: (Opening Inventory + Closing Inventory)/2 | C13: =(C6+D6)/2 -> 4218.5 | D13: =(D6+E6)/2 -> 4136.5 | E13: =(E6+F6)/2 -> 4173.5 | F13: =(F6+G6)/2 -> 3837.5 | G13: =(G6+H6)/2 -> 3173
A14: AVERAGE RECEIVABLES | B14: (Opening Receivables + Closing Receivables)/2 | C14: =(C7+D7)/2 -> 3408 | D14: =(D7+E7)/2 -> 3038 | E14: =(E7+F7)/2 -> 2657.5 | F14: =(F7+G7)/2 -> 1997 | G14: =(G7+H7)/2 -> 1453.5
A15: AVERAGE PAYABLES | B15: (Opening Payables + Closing Payables)/2 | C15: =(C9+D9)/2 -> 10900.5 | D15: =(D9+E9)/2 -> 10030 | E15: =(E9+F9)/2 -> 9321 | F15: =(F9+G9)/2 -> 8935 | G15: =(G9+H9)/2 -> 8168.5
A16: DAYS INVENTORY OUTSTANDING (DIO) (In Days) | B16: (Average Inventory / COGS)*365 | C16: =(C13/C4)*365 -> 50.354912 | D16: =(D13/D4)*365 -> 50.733283 | E16: =(E13/E4)*365 -> 48.030253 | F16: =(F13/F4)*365 -> 54.427336 | G16: =(G13/G4)*365 -> 52.291178
A17: DAYS SALES OUTSTANDING (DSO) (In Days) | B17: (Average Receivables / Revenue)*365 | C17: =(C14/C3)*365 -> 19.97046 | D17: =(D14/D3)*365 -> 18.188334 | E17: =(E14/E3)*365 -> 16.288897 | F17: =(F14/F3)*365 -> 14.140316 | G17: =(G14/G3)*365 -> 11.453283
A18: DAYS PAYABLE OUTSTANDING (DPO) (In Days) | B18: (Average Payables / COGS)*365 | C18: =(C15/C4)*365 -> 130.11585 | D18: =(D15/D4)*365 -> 123.01579 | E18: =(E15/E4)*365 -> 107.26967 | F18: =(F15/F4)*365 -> 126.72528 | G18: =(G15/G4)*365 -> 134.61723
A19: CASH CONVERSION CYCLE (CCC) (In Days) | B19: DIO + DSO - DPO | C19: =C16+C17-C18 -> -59.790479 | D19: =D16+D17-D18 -> -54.094176 | E19: =E16+E17-E18 -> -42.950525 | F19: =F16+F17-F18 -> -58.157625 | G19: =G16+G17-G18 -> -70.872774
A21: ITC LIMITED
A22: Figures (In Crores) | C22: FY25 | D22: FY24 | E22: FY23 | F22: FY22 | G22: FY21 | H22: FY20
A23: Net Revenue from Operations | C23: 69323.52 | D23: 65440.81 | E23: 66043.27 | F23: 56341.27 | G23: 45485.13 | H23: 45619
A24: COGS | C24: 31735.84 | D24: 26982.1 | E24: 28880.18 | F24: 26232.52 | G24: 19974 | H24: =13121+4289-176 -> 17234
A25: Current Assets | C25: 43893.28 | D25: 41065.54 | E25: 39670.89 | F25: 34232.45 | G25: 34991.99 | H25: 39505.35
A26: Inventory | C26: 15836.14 | D26: 14302.88 | E26: 11914.13 | F26: 10973.59 | G26: 10507.22 | H26: 8965
A27: Trade Receivables | C27: 4719.67 | D27: 4025.82 | E27: 2956.17 | F27: 2461.9 | G27: 2501.7 | H27: 2562
A28: Current Liability | C28: 14334.11 | D28: 13690.4 | E28: 13739.41 | F28: 12163.71 | G28: 10689.68 | H28: 9559.77
A29: Trade Payables | C29: 4807.3 | D29: 4797.83 | E29: 4658.99 | F29: 4417.26 | G29: 4318.73 | H29: 3629
A31: ANALYSIS PART
A32: WORKING CAPITAL | B32: CURRENT ASSETS - CURRENT LIABILITY | C32: =C25-C28 -> 29559.17 | D32: =D25-D28 -> 27375.14 | E32: =E25-E28 -> 25931.48 | F32: =F25-F28 -> 22068.74 | G32: =G25-G28 -> 24302.31 | H32: =H25-H28 -> 29945.58
A33: AVERAGE INVENTORY | B33: (Opening Inventory + Closing Inventory)/2 | C33: =(C26+D26)/2 -> 15069.51 | D33: =(D26+E26)/2 -> 13108.505 | E33: =(E26+F26)/2 -> 11443.86 | F33: =(F26+G26)/2 -> 10740.405 | G33: =(G26+H26)/2 -> 9736.11
A34: AVERAGE RECEIVABLES | B34: (Opening Receivables + Closing Receivables)/2 | C34: =(C27+D27)/2 -> 4372.745 | D34: =(D27+E27)/2 -> 3490.995 | E34: =(E27+F27)/2 -> 2709.035 | F34: =(F27+G27)/2 -> 2481.8 | G34: =(G27+H27)/2 -> 2531.85
A35: AVERAGE PAYABLES | B35: (Opening Payables + Closing Payables)/2 | C35: =(C29+D29)/2 -> 4802.565 | D35: =(D29+E29)/2 -> 4728.41 | E35: =(E29+F29)/2 -> 4538.125 | F35: =(F29+G29)/2 -> 4367.995 | G35: =(G29+H29)/2 -> 3973.865
A36: DAYS INVENTORY OUTSTANDING (DIO) (In Days) | B36: (Average Inventory / COGS)*365 | C36: =(C33/C24)*365 -> 173.31733 | D36: =(D33/D24)*365 -> 177.32513 | E36: =(E33/E24)*365 -> 144.63237 | F36: =(F33/F24)*365 -> 149.44229 | G36: =(G33/G24)*365 -> 177.9153
A37: DAYS SALES OUTSTANDING (DSO) (In Days) | B37: (Average Receivables / Revenue)*365 | C37: =(C34/C23)*365 -> 23.023238 | D37: =(D34/D23)*365 -> 19.471232 | E37: =(E34/E23)*365 -> 14.971969 | F37: =(F34/F23)*365 -> 16.078037 | G37: =(G34/G23)*365 -> 20.317085
A38: DAYS PAYABLE OUTSTANDING (DPO) (In Days) | B38: (Average Payables / COGS)*365 | C38: =(C35/C24)*365 -> 55.235224 | D38: =(D35/D24)*365 -> 63.963504 | E38: =(E35/E24)*365 -> 57.354754 | F38: =(F35/F24)*365 -> 60.776402 | G38: =(G35/G24)*365 -> 72.617439
A39: CASH CONVERSION CYCLE (CCC) (In Days) | B39: DIO + DSO - DPO | C39: =C36+C37-C38 -> 141.10535 | D39: =D36+D37-D38 -> 132.83286 | E39: =E36+E37-E38 -> 102.24959 | F39: =F36+F37-F38 -> 104.74392 | G39: =G36+G37-G38 -> 125.61494
A41: NESTLE INDIA LTD
A42: Figures (In Crores) | C42: FY25 | D42: FY24 | E42: FY23 | F42: FY22 | G42: FY21 | H42: FY20
A43: Net Revenue from Operations | C43: 20077.5 | D43: 24275.48 | E43: 19021.05 | F43: 16789.53 | G43: 14633.72 | H43: 13290.16
A44: COGS | C44: 8749.8 | D44: 10708.57 | E44: 8432.71 | F44: 7749.86 | G44: 6318.92 | H44: =5554.24+189-69 -> 5674.24
A45: Current Assets | C45: 3734.16 | D45: 3494.72 | E45: 3593.77 | F45: 3490.15 | G45: 2738.76 | H45: 4185
A46: Inventory | C46: 2850.14 | D46: 2089.36 | E46: 1873.26 | F46: 1928.77 | G46: 1580.22 | H46: 1416
A47: Trade Receivables | C47: 363.15 | D47: 300.46 | E47: 202.57 | F47: 191.89 | G47: 165.27 | H47: 164.93
A48: Current Liability | C48: 4685.35 | D48: 3956.07 | E48: 3790.64 | F48: 3079.75 | G48: 2603.24 | H48: 2492
A49: Trade Payables | C49: 2623.81 | D49: 2812.01 | E49: 2454 | F49: 2120.94 | G49: 1889.66 | H49: 1809.01
A51: ANALYSIS PART
A52: WORKING CAPITAL | B52: CURRENT ASSETS - CURRENT LIABILITY | C52: =C45-C48 -> -951.19 | D52: =D45-D48 -> -461.35 | E52: =E45-E48 -> -196.87 | F52: =F45-F48 -> 410.4 | G52: =G45-G48 -> 135.52 | H52: =H45-H48 -> 1693
A53: AVERAGE INVENTORY | B53: (Opening Inventory + Closing Inventory)/2 | C53: =(C46+D46)/2 -> 2469.75 | D53: =(D46+E46)/2 -> 1981.31 | E53: =(E46+F46)/2 -> 1901.015 | F53: =(F46+G46)/2 -> 1754.495 | G53: =(G46+H46)/2 -> 1498.11
A54: AVERAGE RECEIVABLES | B54: (Opening Receivables + Closing Receivables)/2 | C54: =(C47+D47)/2 -> 331.805 | D54: =(D47+E47)/2 -> 251.515 | E54: =(E47+F47)/2 -> 197.23 | F54: =(F47+G47)/2 -> 178.58 | G54: =(G47+H47)/2 -> 165.1
A55: AVERAGE PAYABLES | B55: (Opening Payables + Closing Payables)/2 | C55: =(C49+D49)/2 -> 2717.91 | D55: =(D49+E49)/2 -> 2633.005 | E55: =(E49+F49)/2 -> 2287.47 | F55: =(F49+G49)/2 -> 2005.3 | G55: =(G49+H49)/2 -> 1849.335
A56: DAYS INVENTORY OUTSTANDING (DIO) (In Days) | B56: (Average Inventory / COGS)*365 | C56: =(C53/C44)*365 -> 103.02621 | D56: =(D53/D44)*365 -> 67.532654 | E56: =(E53/E44)*365 -> 82.283213 | F56: =(F53/F44)*365 -> 82.632548 | G56: =(G53/G44)*365 -> 86.535381
A57: DAYS SALES OUTSTANDING (DSO) (In Days) | B57: (Average Receivables / Revenue)*365 | C57: =(C54/C43)*365 -> 6.032067 | D57: =(D54/D43)*365 -> 3.7817162 | E57: =(E54/E43)*365 -> 3.7846991 | F57: =(F54/F43)*365 -> 3.8822826 | G57: =(G54/G43)*365 -> 4.1179891
A58: DAYS PAYABLE OUTSTANDING (DPO) (In Days) | B58: (Average Payables / COGS)*365 | C58: =(C55/C44)*365 -> 113.37827 | D58: =(D55/D44)*365 -> 89.74558 | E58: =(E55/E44)*365 -> 99.010466 | F58: =(F55/F44)*365 -> 94.444867 | G58: =(G55/G44)*365 -> 106.8232
A59: CASH CONVERSION CYCLE (CCC) (In Days) | B59: DIO + DSO - DPO | C59: =C56+C57-C58 -> -4.3199868 | D59: =D56+D57-D58 -> -18.43121 | E59: =E56+E57-E58 -> -12.942554 | F59: =F56+F57-F58 -> -7.9300372 | G59: =G56+G57-G58 -> -16.169833
A61: VARUN BEVRAGES LTD
A62: Figures (In Crores) | C62: CY25 | D62: CY24 | E62: CY23 | F62: CY22 | G62: CY21 | H62: CY20
A63: Net Revenue from Operations | C63: 21685.38 | D63: 20007.65 | E63: 16042.58 | F63: 13173.14 | G63: 8823.23 | H63: 6360
A64: COGS | C64: 9715.42 | D64: 8904.72 | E64: 7404.89 | F64: 6261.15 | G64: 4034.66 | H64: =2688+92-17 -> 2763
A65: Current Assets | C65: 7896.04 | D65: 7863.97 | E65: 4235.63 | F65: 3404.03 | G65: 2546.11 | H65: 1800
A66: Inventory | C66: 2951.79 | D66: 2791.23 | E66: 2150.53 | F66: 1993.89 | G66: 1448.09 | H66: 928
A67: Trade Receivables | C67: 1249.03 | D67: 845.84 | E67: 359.39 | F67: 299.34 | G67: 221.25 | H67: 241.8
A68: Current Liability | C68: 4073.95 | D68: 4524.43 | E68: 4153.21 | F68: 3968.75 | G68: 3020.25 | H68: 2435
A69: Trade Payables | C69: 1401.3 | D69: 1560.43 | E69: 758.25 | F69: 824.26 | G69: 711.75 | H69: 511.39
A71: ANALYSIS PART
A72: WORKING CAPITAL | B72: CURRENT ASSETS - CURRENT LIABILITY | C72: =C65-C68 -> 3822.09 | D72: =D65-D68 -> 3339.54 | E72: =E65-E68 -> 82.42 | F72: =F65-F68 -> -564.72 | G72: =G65-G68 -> -474.14 | H72: =H65-H68 -> -635
A73: AVERAGE INVENTORY | B73: (Opening Inventory + Closing Inventory)/2 | C73: =(C66+D66)/2 -> 2871.51 | D73: =(D66+E66)/2 -> 2470.88 | E73: =(E66+F66)/2 -> 2072.21 | F73: =(F66+G66)/2 -> 1720.99 | G73: =(G66+H66)/2 -> 1188.045
A74: AVERAGE RECEIVABLES | B74: (Opening Receivables + Closing Receivables)/2 | C74: =(C67+D67)/2 -> 1047.435 | D74: =(D67+E67)/2 -> 602.615 | E74: =(E67+F67)/2 -> 329.365 | F74: =(F67+G67)/2 -> 260.295 | G74: =(G67+H67)/2 -> 231.525
A75: AVERAGE PAYABLES | B75: (Opening Payables + Closing Payables)/2 | C75: =(C69+D69)/2 -> 1480.865 | D75: =(D69+E69)/2 -> 1159.34 | E75: =(E69+F69)/2 -> 791.255 | F75: =(F69+G69)/2 -> 768.005 | G75: =(G69+H69)/2 -> 611.57
A76: DAYS INVENTORY OUTSTANDING (DIO) (In Days) | B76: (Average Inventory / COGS)*365 | C76: =(C73/C64)*365 -> 107.88017 | D76: =(D73/D64)*365 -> 101.28013 | E76: =(E73/E64)*365 -> 102.14286 | F76: =(F73/F64)*365 -> 100.32683 | G76: =(G73/G64)*365 -> 107.47781
A77: DAYS SALES OUTSTANDING (DSO) (In Days) | B77: (Average Receivables / Revenue)*365 | C77: =(C74/C63)*365 -> 17.630024 | D77: =(D74/D63)*365 -> 10.993519 | E77: =(E74/E63)*365 -> 7.4936965 | F77: =(F74/F63)*365 -> 7.2122269 | G77: =(G74/G63)*365 -> 9.5777425
A78: DAYS PAYABLE OUTSTANDING (DPO) (In Days) | B78: (Average Payables / COGS)*365 | C78: =(C75/C64)*365 -> 55.634828 | D78: =(D75/D64)*365 -> 47.520764 | E78: =(E75/E64)*365 -> 39.002345 | F78: =(F75/F64)*365 -> 44.771619 | G78: =(G75/G64)*365 -> 55.32636
A79: CASH CONVERSION CYCLE (CCC) (In Days) | B79: DIO + DSO - DPO | C79: =C76+C77-C78 -> 69.875365 | D79: =D76+D77-D78 -> 64.752885 | E79: =E76+E77-E78 -> 70.634212 | F79: =F76+F77-F78 -> 62.76744 | G79: =G76+G77-G78 -> 61.729194
A81: BRITANNIA INDUSTRIES LTD
A82: Figures (In Crores) | C82: FY25 | D82: FY24 | E82: FY23 | F82: FY22 | G82: FY21 | H82: FY20
A83: Net Revenue from Operations | C83: 17942.67 | D83: 16769.27 | E83: 16300.55 | F83: 14136.26 | G83: 13136.14 | H83: 11599.55
A84: COGS | C84: 10604.05 | D84: 9492.03 | E84: 9591.3 | F84: 8760.3 | G84: 7626.1 | H84: =5684+1189+53 -> 6926
A85: Current Assets | C85: 3913.68 | D85: 4848.66 | E85: 4746.23 | F85: 3970.42 | G85: 4419.68 | H85: 3674.97
A86: Inventory | C86: 1236.51 | D86: 1181.22 | E86: 1193.26 | F86: 1367.49 | G86: 1091.49 | H86: 740.96
A87: Trade Receivables | C87: 448.61 | D87: 393.33 | E87: 328.94 | F87: 331.93 | G87: 257.27 | H87: 320.36
A88: Current Liability | C88: 3618.26 | D88: 4084.41 | E88: 4134.4 | F88: 4155.73 | G88: 3614.2 | H88: 2578.46
A89: Trade Payables | C89: 1752.23 | D89: 1627.48 | E89: 1448.81 | F89: 1285.22 | G89: 1314.75 | H89: 1047
A91: ANALYSIS PART
A92: WORKING CAPITAL | B92: CURRENT ASSETS - CURRENT LIABILITY | C92: =C85-C88 -> 295.42 | D92: =D85-D88 -> 764.25 | E92: =E85-E88 -> 611.83 | F92: =F85-F88 -> -185.31 | G92: =G85-G88 -> 805.48 | H92: =H85-H88 -> 1096.51
A93: AVERAGE INVENTORY | B93: (Opening Inventory + Closing Inventory)/2 | C93: =(C86+D86)/2 -> 1208.865 | D93: =(D86+E86)/2 -> 1187.24 | E93: =(E86+F86)/2 -> 1280.375 | F93: =(F86+G86)/2 -> 1229.49 | G93: =(G86+H86)/2 -> 916.225
A94: AVERAGE RECEIVABLES | B94: (Opening Receivables + Closing Receivables)/2 | C94: =(C87+D87)/2 -> 420.97 | D94: =(D87+E87)/2 -> 361.135 | E94: =(E87+F87)/2 -> 330.435 | F94: =(F87+G87)/2 -> 294.6 | G94: =(G87+H87)/2 -> 288.815
A95: AVERAGE PAYABLES | B95: (Opening Payables + Closing Payables)/2 | C95: =(C89+D89)/2 -> 1689.855 | D95: =(D89+E89)/2 -> 1538.145 | E95: =(E89+F89)/2 -> 1367.015 | F95: =(F89+G89)/2 -> 1299.985 | G95: =(G89+H89)/2 -> 1180.875
A96: DAYS INVENTORY OUTSTANDING (DIO) (In Days) | B96: (Average Inventory / COGS)*365 | C96: =(C93/C84)*365 -> 41.610114 | D96: =(D93/D84)*365 -> 45.653311 | E96: =(E93/E84)*365 -> 48.725082 | F96: =(F93/F84)*365 -> 51.226996 | G96: =(G93/G84)*365 -> 43.852313
A97: DAYS SALES OUTSTANDING (DSO) (In Days) | B97: (Average Receivables / Revenue)*365 | C97: =(C94/C83)*365 -> 8.5636112 | D97: =(D94/D83)*365 -> 7.8604659 | E97: =(E94/E83)*365 -> 7.3990617 | F97: =(F94/F83)*365 -> 7.6066088 | G97: =(G94/G83)*365 -> 8.0249963
A98: DAYS PAYABLE OUTSTANDING (DPO) (In Days) | B98: (Average Payables / COGS)*365 | C98: =(C95/C84)*365 -> 58.166179 | D98: =(D95/D84)*365 -> 59.146771 | E98: =(E95/E84)*365 -> 52.022195 | F98: =(F95/F84)*365 -> 54.164187 | G98: =(G95/G84)*365 -> 56.518978
A99: CASH CONVERSION CYCLE (CCC) (In Days) | B99: DIO + DSO - DPO | C99: =C96+C97-C98 -> -7.9924546 | D99: =D96+D97-D98 -> -5.6329939 | E99: =E96+E97-E98 -> 4.1019487 | F99: =F96+F97-F98 -> 4.6694177 | G99: =G96+G97-G98 -> -4.6416682
A101: GODFREY PHILLIPS INDIA
A102: Figures (In Crores) | C102: FY25 | D102: FY24 | E102: FY23 | F102: FY22 | G102: FY21 | H102: FY20
A103: Net Revenue from Operations | C103: 5611.01 | D103: 4419.58 | E103: 3562.49 | F103: 2687.57 | G103: 2525.34 | H103: 2876.58
A104: COGS | C104: 3252.71 | D104: 2444.99 | E104: 1781.49 | F104: 1225.77 | G104: 1223.15 | H104: =705.6+571-15 -> 1261.6
A105: Current Assets | C105: 3002.07 | D105: 2011.61 | E105: 1419.43 | F105: 1648.61 | G105: 1523.76 | H105: 1056.74
A106: Inventory | C106: 1997.08 | D106: 1441.59 | E106: 928.15 | F106: 828.71 | G106: 743.11 | H106: 687
A107: Trade Receivables | C107: 516.35 | D107: 172.87 | E107: 149.52 | F107: 154.64 | G107: 122.99 | H107: 69
A108: Current Liability | C108: 1431.54 | D108: 1213.94 | E108: 1039.78 | F108: 822.29 | G108: 790.64 | H108: 738.57
A109: Trade Payables | C109: 499.62 | D109: 466.77 | E109: 365.49 | F109: 252.87 | G109: 233.19 | H109: 254.02
A111: ANALYSIS PART
...

Sheet Automotive
A1: TATA MOTORS
A2: Figures (In Crores) | C2: FY25 | D2: FY24 | E2: FY23 | F2: FY22 | G2: FY21 | H2: FY20
A3: Net Revenue from Operations | C3: 439695 | D3: 437927.77 | E3: 345966.96 | F3: 278453.62 | G3: 249794.75 | H3: 261067.97
A4: COGS | C4: 282418 | D4: 283762.32 | E4: 237145.35 | F4: 190109.77 | G4: 163518.15 | H4: =152671+12228+4188+2232 -> 171319
A5: Current Assets | C5: 160325 | D5: 168392.15 | E5: 151528.47 | F5: 146977.54 | G5: 146887.64 | H5: 119587.25
A6: Inventory | C6: 47269 | D6: 47788.29 | E6: 40755.39 | F6: 35240.34 | G6: 36088.59 | H6: 37456.88
A7: Trade Receivables | C7: 13248 | D7: 16951.81 | E7: 15737.97 | F7: 12442.12 | G7: 12679.08 | H7: 11172.69
A8: Current Liability | C8: 166684 | D8: 173617 | E8: 155027.33 | F8: 150682.81 | G8: 157749.18 | H8: 140454.05
A9: Trade Payables | C9: 97368 | D9: 88042.95 | E9: 72055.77 | F9: 59970.38 | G9: 68179.8 | H9: 63626.88
A11: ANALYSIS PART
A12: WORKING CAPITAL | B12: CURRENT ASSETS - CURRENT LIABILITY | C12: =C5-C8 -> -6359 | D12: =D5-D8 -> -5224.85 | E12: =E5-E8 -> -3498.86 | F12: =F5-F8 -> -3705.27 | G12: =G5-G8 -> -10861.54 | H12: =H5-H8 -> -20866.8
A13: AVERAGE INVENTORY | B13: (Opening Inventory + Closing Inventory)/2 | C13: =(C6+D6)/2 -> 47528.645 | D13: =(D6+E6)/2 -> 44271.84 | E13: =(E6+F6)/2 -> 37997.865 | F13: =(F6+G6)/2 -> 35664.465 | G13: =(G6+H6)/2 -> 36772.735
A14: AVERAGE RECEIVABLES | B14: (Opening Receivables + Closing Receivables)/2 | C14: =(C7+D7)/2 -> 15099.905 | D14: =(D7+E7)/2 -> 16344.89 | E14: =(E7+F7)/2 -> 14090.045 | F14: =(F7+G7)/2 -> 12560.6 | G14: =(G7+H7)/2 -> 11925.885
A15: AVERAGE PAYABLES | B15: (Opening Payables + Closing Payables)/2 | C15: =(C9+D9)/2 -> 92705.475 | D15: =(D9+E9)/2 -> 80049.36 | E15: =(E9+F9)/2 -> 66013.075 | F15: =(F9+G9)/2 -> 64075.09 | G15: =(G9+H9)/2 -> 65903.34
A16: DAYS INVENTORY OUTSTANDING (DIO) (In Days) | B16: (Average Inventory / COGS)*365 | C16: =(C13/C4)*365 -> 61.426522 | D16: =(D13/D4)*365 -> 56.946326 | E16: =(E13/E4)*365 -> 58.484051 | F16: =(F13/F4)*365 -> 68.473755 | G16: =(G13/G4)*365 -> 82.082926
A17: DAYS SALES OUTSTANDING (DSO) (In Days) | B17: (Average Receivables / Revenue)*365 | C17: =(C14/C3)*365 -> 12.534746 | D17: =(D14/D3)*365 -> 13.622988 | E17: =(E14/E3)*365 -> 14.865195 | F17: =(F14/F3)*365 -> 16.46457 | G17: =(G14/G3)*365 -> 17.426099
A18: DAYS PAYABLE OUTSTANDING (DPO) (In Days) | B18: (Average Payables / COGS)*365 | C18: =(C15/C4)*365 -> 119.81353 | D18: =(D15/D4)*365 -> 102.96651 | E18: =(E15/E4)*365 -> 101.60339 | F18: =(F15/F4)*365 -> 123.02055 | G18: =(G15/G4)*365 -> 147.10733
A19: CASH CONVERSION CYCLE (CCC) (In Days) | B19: DIO + DSO - DPO | C19: =C16+C17-C18 -> -45.852265 | D19: =D16+D17-D18 -> -32.397198 | E19: =E16+E17-E18 -> -28.254148 | F19: =F16+F17-F18 -> -38.082223 | G19: =G16+G17-G18 -> -47.598309
A21: MAHINDRA AND MAHINDRA
A22: Figures (In Crores) | C22: FY25 | D22: FY24 | E22: FY23 | F22: FY22 | G22: FY21 | H22: FY20
A23: Net Revenue from Operations | C23: 158749.75 | D23: 138279.3 | E23: 121268.55 | F23: 90170.57 | G23: 74277.78 | H23: 75381.93
A24: COGS | C24: 95742.72 | D24: 83624.75 | E24: 73987.56 | F24: 51803.19 | G24: 38406.79 | H24: 38421.9
A25: Current Assets | C25: 126573.27 | D25: 98265.64 | E25: 91325.44 | F25: 75148 | G25: 72137.91 | H25: 64045.43
A26: Inventory | C26: 20330.93 | D26: 18590.47 | E26: 16854.97 | F26: 11595.82 | G26: 9615.41 | H26: 11111.86
A27: Trade Receivables | C27: 8279.7 | D27: 7459.4 | E27: 7028.02 | F27: 6373.95 | G27: 6007.76 | H27: 6928.28
A28: Current Liability | C28: 90322.01 | D28: 75545.65 | E28: 70579.41 | F28: 56288.33 | G28: 51446.01 | H28: 54009.52
A29: Trade Payables | C29: 30855.3 | D29: 25665.64 | E29: 23835.66 | F29: 19036.55 | G29: 15505.79 | H29: 14985.35
A31: ANALYSIS PART
A32: WORKING CAPITAL | B32: CURRENT ASSETS - CURRENT LIABILITY | C32: =C25-C28 -> 36251.26 | D32: =D25-D28 -> 22719.99 | E32: =E25-E28 -> 20746.03 | F32: =F25-F28 -> 18859.67 | G32: =G25-G28 -> 20691.9 | H32: =H25-H28 -> 10035.91
A33: AVERAGE INVENTORY | B33: (Opening Inventory + Closing Inventory)/2 | C33: =(C26+D26)/2 -> 19460.7 | D33: =(D26+E26)/2 -> 17722.72 | E33: =(E26+F26)/2 -> 14225.395 | F33: =(F26+G26)/2 -> 10605.615 | G33: =(G26+H26)/2 -> 10363.635
A34: AVERAGE RECEIVABLES | B34: (Opening Receivables + Closing Receivables)/2 | C34: =(C27+D27)/2 -> 7869.55 | D34: =(D27+E27)/2 -> 7243.71 | E34: =(E27+F27)/2 -> 6700.985 | F34: =(F27+G27)/2 -> 6190.855 | G34: =(G27+H27)/2 -> 6468.02
A35: AVERAGE PAYABLES | B35: (Opening Payables + Closing Payables)/2 | C35: =(C29+D29)/2 -> 28260.47 | D35: =(D29+E29)/2 -> 24750.65 | E35: =(E29+F29)/2 -> 21436.105 | F35: =(F29+G29)/2 -> 17271.17 | G35: =(G29+H29)/2 -> 15245.57
A36: DAYS INVENTORY OUTSTANDING (DIO) (In Days) | B36: (Average Inventory / COGS)*365 | C36: =(C33/C24)*365 -> 74.190032 | D36: =(D33/D24)*365 -> 77.355003 | E36: =(E33/E24)*365 -> 70.177597 | F36: =(F33/F24)*365 -> 74.726083 | G36: =(G33/G24)*365 -> 98.491094
A37: DAYS SALES OUTSTANDING (DSO) (In Days) | B37: (Average Receivables / Revenue)*365 | C37: =(C34/C23)*365 -> 18.093797 | D37: =(D34/D23)*365 -> 19.12039 | E37: =(E34/E23)*365 -> 20.168952 | F37: =(F34/F23)*365 -> 25.059862 | G37: =(G34/G23)*365 -> 31.783762
A38: DAYS PAYABLE OUTSTANDING (DPO) (In Days) | B38: (Average Payables / COGS)*365 | C38: =(C35/C24)*365 -> 107.7374 | D38: =(D35/D24)*365 -> 108.03007 | E38: =(E35/E24)*365 -> 105.74992 | F38: =(F35/F24)*365 -> 121.6909 | G38: =(G35/G24)*365 -> 144.8867
A39: CASH CONVERSION CYCLE (CCC) (In Days) | B39: DIO + DSO - DPO | C39: =C36+C37-C38 -> -15.453569 | D39: =D36+D37-D38 -> -11.554673 | E39: =E36+E37-E38 -> -15.403368 | F39: =F36+F37-F38 -> -21.904959 | G39: =G36+G37-G38 -> -14.611843
A41: MARUTI SUZUKI INDIA
A42: Figures (In Crores) | C42: FY25 | D42: FY24 | E42: FY23 | F42: FY22 | G42: FY21 | H42: FY20
A43: Net Revenue from Operations | C43: 152913 | D43: 141858.2 | E43: 117571.3 | F43: 88329.8 | G43: 70372 | H43: 75660
A44: COGS | C44: 107490.8 | D44: 99740.9 | E44: 86250.8 | F44: 66044 | G44: 50824.1 | H44: =34634+18767.2-238.7 -> 53162.5
A45: Current Assets | C45: 29524.2 | D45: 22633.8 | E45: 11615.6 | F45: 16793.4 | G45: 18544.3 | H45: 8440.6
A46: Inventory | C46: 6913.2 | D46: 5318.1 | E46: 4283.5 | F46: 3532.3 | G46: 3049 | H46: 3213.9
A47: Trade Receivables | C47: 6539.7 | D47: 4596.8 | E47: 3301.4 | F47: 2034.5 | G47: 1279.9 | H47: 1977.7
A48: Current Liability | C48: 30570.5 | D48: 25951.8 | E48: 20107.3 | F48: 17023.5 | G48: 16120.5 | H48: 11305.4
A49: Trade Payables | C49: 20501.5 | D49: 16988.4 | E49: 11785.5 | F49: 9765.2 | G49: 10168.1 | H49: 7498.8
A51: ANALYSIS PART
A52: WORKING CAPITAL | B52: CURRENT ASSETS - CURRENT LIABILITY | C52: =C45-C48 -> -1046.3 | D52: =D45-D48 -> -3318 | E52: =E45-E48 -> -8491.7 | F52: =F45-F48 -> -230.1 | G52: =G45-G48 -> 2423.8 | H52: =H45-H48 -> -2864.8
A53: AVERAGE INVENTORY | B53: (Opening Inventory + Closing Inventory)/2 | C53: =(C46+D46)/2 -> 6115.65 | D53: =(D46+E46)/2 -> 4800.8 | E53: =(E46+F46)/2 -> 3907.9 | F53: =(F46+G46)/2 -> 3290.65 | G53: =(G46+H46)/2 -> 3131.45
A54: AVERAGE RECEIVABLES | B54: (Opening Receivables + Closing Receivables)/2 | C54: =(C47+D47)/2 -> 5568.25 | D54: =(D47+E47)/2 -> 3949.1 | E54: =(E47+F47)/2 -> 2667.95 | F54: =(F47+G47)/2 -> 1657.2 | G54: =(G47+H47)/2 -> 1628.8
A55: AVERAGE PAYABLES | B55: (Opening Payables + Closing Payables)/2 | C55: =(C49+D49)/2 -> 18744.95 | D55: =(D49+E49)/2 -> 14386.95 | E55: =(E49+F49)/2 -> 10775.35 | F55: =(F49+G49)/2 -> 9966.65 | G55: =(G49+H49)/2 -> 8833.45
A56: DAYS INVENTORY OUTSTANDING (DIO) (In Days) | B56: (Average Inventory / COGS)*365 | C56: =(C53/C44)*365 -> 20.766542 | D56: =(D53/D44)*365 -> 17.56844 | E56: =(E53/E44)*365 -> 16.537626 | F56: =(F53/F44)*365 -> 18.186168 | G56: =(G53/G44)*365 -> 22.488923
A57: DAYS SALES OUTSTANDING (DSO) (In Days) | B57: (Average Receivables / Revenue)*365 | C57: =(C54/C43)*365 -> 13.291291 | D57: =(D54/D43)*365 -> 10.161002 | E57: =(E54/E43)*365 -> 8.2826485 | F57: =(F54/F43)*365 -> 6.8479494 | G57: =(G54/G43)*365 -> 8.4481328
A58: DAYS PAYABLE OUTSTANDING (DPO) (In Days) | B58: (Average Payables / COGS)*365 | C58: =(C55/C44)*365 -> 63.651092 | D58: =(D55/D44)*365 -> 52.64878 | E58: =(E55/E44)*365 -> 45.599609 | F58: =(F55/F44)*365 -> 55.081873 | G58: =(G55/G44)*365 -> 63.43859
A59: CASH CONVERSION CYCLE (CCC) (In Days) | B59: DIO + DSO - DPO | C59: =C56+C57-C58 -> -29.593258 | D59: =D56+D57-D58 -> -24.919338 | E59: =E56+E57-E58 -> -20.779334 | F59: =F56+F57-F58 -> -30.047757 | G59: =G56+G57-G58 -> -32.501535
A61: SAMVARDHANA MOTHERSON INTERNATIONAL
A62: Figures (In Crores) | C62: FY25 | D62: FY24 | E62: FY23 | F62: FY22 | G62: FY21 | H62: FY20
A63: Net Revenue from Operations | C63: 113662.6 | D63: 98691.7 | E63: 78700.7 | F63: 63536 | G63: 57369.9 | H63: 60728.9
A64: COGS | C64: 61052.2 | D64: 54414.7 | E64: 45317.4 | F64: 36736.3 | G64: 32597.9 | H64: =34285+710-26 -> 34969
A65: Current Assets | C65: 43307.9 | D65: 40272.2 | E65: 26779.2 | F65: 22616.3 | G65: 22027.5 | H65: 19465.4
A66: Inventory | C66: 10787.3 | D66: 9138.6 | E66: 7822.8 | F66: 6441.7 | G66: 4995.6 | H66: 5156.6
A67: Trade Receivables | C67: 17430.7 | D67: 15637.1 | E67: 8513.5 | F67: 6573.1 | G67: 5693.1 | H67: 5178.4
A68: Current Liability | C68: 42069.4 | D68: 41720.4 | E68: 27515.4 | F68: 22285.3 | G68: 21129.6 | H68: 19570.8
A69: Trade Payables | C69: 23669.2 | D69: 22617.2 | E69: 14136.3 | F69: 11360.3 | G69: 11140.6 | H69: 10309.1
A71: ANALYSIS PART
A72: WORKING CAPITAL | B72: CURRENT ASSETS - CURRENT LIABILITY | C72: =C65-C68 -> 1238.5 | D72: =D65-D68 -> -1448.2 | E72: =E65-E68 -> -736.2 | F72: =F65-F68 -> 331 | G72: =G65-G68 -> 897.9 | H72: =H65-H68 -> -105.4
A73: AVERAGE INVENTORY | B73: (Opening Inventory + Closing Inventory)/2 | C73: =(C66+D66)/2 -> 9962.95 | D73: =(D66+E66)/2 -> 8480.7 | E73: =(E66+F66)/2 -> 7132.25 | F73: =(F66+G66)/2 -> 5718.65 | G73: =(G66+H66)/2 -> 5076.1
A74: AVERAGE RECEIVABLES | B74: (Opening Receivables + Closing Receivables)/2 | C74: =(C67+D67)/2 -> 16533.9 | D74: =(D67+E67)/2 -> 12075.3 | E74: =(E67+F67)/2 -> 7543.3 | F74: =(F67+G67)/2 -> 6133.1 | G74: =(G67+H67)/2 -> 5435.75
A75: AVERAGE PAYABLES | B75: (Opening Payables + Closing Payables)/2 | C75: =(C69+D69)/2 -> 23143.2 | D75: =(D69+E69)/2 -> 18376.75 | E75: =(E69+F69)/2 -> 12748.3 | F75: =(F69+G69)/2 -> 11250.45 | G75: =(G69+H69)/2 -> 10724.85
A76: DAYS INVENTORY OUTSTANDING (DIO) (In Days) | B76: (Average Inventory / COGS)*365 | C76: =(C73/C64)*365 -> 59.563402 | D76: =(D73/D64)*365 -> 56.886384 | E76: =(E73/E64)*365 -> 57.445291 | F76: =(F73/F64)*365 -> 56.818658 | G76: =(G73/G64)*365 -> 56.837296
A77: DAYS SALES OUTSTANDING (DSO) (In Days) | B77: (Average Receivables / Revenue)*365 | C77: =(C74/C63)*365 -> 53.094628 | D77: =(D74/D63)*365 -> 44.65912 | E77: =(E74/E63)*365 -> 34.984498 | F77: =(F74/F63)*365 -> 35.233277 | G77: =(G74/G63)*365 -> 34.583444
A78: DAYS PAYABLE OUTSTANDING (DPO) (In Days) | B78: (Average Payables / COGS)*365 | C78: =(C75/C64)*365 -> 138.3614 | D78: =(D75/D64)*365 -> 123.26658 | E78: =(E75/E64)*365 -> 102.67865 | F78: =(F75/F64)*365 -> 111.78083 | G78: =(G75/G64)*365 -> 120.08658
A79: CASH CONVERSION CYCLE (CCC) (In Days) | B79: DIO + DSO - DPO | C79: =C76+C77-C78 -> -25.703372 | D79: =D76+D77-D78 -> -21.721072 | E79: =E76+E77-E78 -> -10.248861 | F79: =F76+F77-F78 -> -19.728899 | G79: =G76+G77-G78 -> -28.665837
A81: HYUNDAI MOTOR INDIA
A82: Figures (In Crores) | C82: FY25 | D82: FY24 | E82: FY23 | F82: FY22 | G82: FY21 | H82: FY20
A83: Net Revenue from Operations | C83: 69192.89 | D83: 69829.06 | E83: 60307.58 | F83: 47378.43 | G83: 40674.01 | H83: 42978.63
A84: COGS | C84: 49970.39 | D84: 51592.95 | E84: 45029.94 | F84: 35825.1 | G84: =30469.68+755.3+104.81 -> 31329.79 | H84: =31706.7+1050+46.35 -> 32803.05
A85: Current Assets | C85: 16032.34 | D85: 16124.04 | E85: 25361.97 | F85: 20079.84 | G85: 17177.13 | H85: 13770.65
A86: Inventory | C86: 3404.36 | D86: 3315.63 | E86: 3422.41 | F86: 2881.12 | G86: 2563.32 | H86: 2769.98
A87: Trade Receivables | C87: 2389.12 | D87: 2510.03 | E87: 2897.19 | F87: 2182.41 | G87: 2440.62 | H87: 1498.31
A88: Current Liability | C88: 11266.32 | D88: 12997.19 | E88: 12005.52 | F88: 9192.24 | G88: 9117.57 | H88: 6648.68
A89: Trade Payables | C89: 7086.21 | D89: 7493.06 | E89: 7440.83 | F89: 5405.43 | G89: 6053.95 | H89: 4619.27
A91: ANALYSIS PART
A92: WORKING CAPITAL | B92: CURRENT ASSETS - CURRENT LIABILITY | C92: =C85-C88 -> 4766.02 | D92: =D85-D88 -> 3126.85 | E92: =E85-E88 -> 13356.45 | F92: =F85-F88 -> 10887.6 | G92: =G85-G88 -> 8059.56 | H92: =H85-H88 -> 7121.97
A93: AVERAGE INVENTORY | B93: (Opening Inventory + Closing Inventory)/2 | C93: =(C86+D86)/2 -> 3359.995 | D93: =(D86+E86)/2 -> 3369.02 | E93: =(E86+F86)/2 -> 3151.765 | F93: =(F86+G86)/2 -> 2722.22 | G93: =(G86+H86)/2 -> 2666.65
A94: AVERAGE RECEIVABLES | B94: (Opening Receivables + Closing Receivables)/2 | C94: =(C87+D87)/2 -> 2449.575 | D94: =(D87+E87)/2 -> 2703.61 | E94: =(E87+F87)/2 -> 2539.8 | F94: =(F87+G87)/2 -> 2311.515 | G94: =(G87+H87)/2 -> 1969.465
A95: AVERAGE PAYABLES | B95: (Opening Payables + Closing Payables)/2 | C95: =(C89+D89)/2 -> 7289.635 | D95: =(D89+E89)/2 -> 7466.945 | E95: =(E89+F89)/2 -> 6423.13 | F95: =(F89+G89)/2 -> 5729.69 | G95: =(G89+H89)/2 -> 5336.61
A96: DAYS INVENTORY OUTSTANDING (DIO) (In Days) | B96: (Average Inventory / COGS)*365 | C96: =(C93/C84)*365 -> 24.542498 | D96: =(D93/D84)*365 -> 23.834503 | E96: =(E93/E84)*365 -> 25.547319 | F96: =(F93/F84)*365 -> 27.735032 | G96: =(G93/G84)*365 -> 31.067149
A97: DAYS SALES OUTSTANDING (DSO) (In Days) | B97: (Average Receivables / Revenue)*365 | C97: =(C94/C83)*365 -> 12.921774 | D97: =(D94/D83)*365 -> 14.131905 | E97: =(E94/E83)*365 -> 15.37165 | F97: =(F94/F83)*365 -> 17.807744 | G97: =(G94/G83)*365 -> 17.673564
A98: DAYS PAYABLE OUTSTANDING (DPO) (In Days) | B98: (Average Payables / COGS)*365 | C98: =(C95/C84)*365 -> 53.245868 | D98: =(D95/D84)*365 -> 52.825724 | E98: =(E95/E84)*365 -> 52.064081 | F98: =(F95/F84)*365 -> 58.376302 | G98: =(G95/G84)*365 -> 62.17286
A99: CASH CONVERSION CYCLE (CCC) (In Days) | B99: DIO + DSO - DPO | C99: =C96+C97-C98 -> -15.781596 | D99: =D96+D97-D98 -> -14.859316 | E99: =E96+E97-E98 -> -11.145113 | F99: =F96+F97-F98 -> -12.833525 | G99: =G96+G97-G98 -> -13.432147
A101: SKF INDIA
A102: Figures (In Crores) | C102: FY25 | D102: FY24 | E102: FY23 | F102: FY22 | G102: FY21 | H102: FY20
A103: Net Revenue from Operations | C103: 4919.92 | D103: 4570.13 | E103: 4304.92 | F103: 3665.89 | G103: 2670.73 | H103: 2841.58
A104: COGS | C104: 3016.54 | D104: 2778.29 | E104: 2565.82 | F104: 2245.19 | G104: 1561.24 | H104: =602.8+1203.22-15 -> 1791.02
A105: Current Assets | C105: 2568.5 | D105: 2741.21 | E105: 2448.56 | F105: 1958.37 | G105: 1631.47 | H105: 1840.12
A106: Inventory | C106: 873.33 | D106: 683.88 | E106: 686.03 | F106: 676.82 | G106: 468 | H106: 451.78
A107: Trade Receivables | C107: 848.55 | D107: 751.33 | E107: 678.65 | F107: 687.13 | G107: 583.44 | H107: 435.7
A108: Current Liability | C108: 910.31 | D108: 927.96 | E108: 796.11 | F108: 695.19 | G108: 693.11 | H108: 516.5
A109: Trade Payables | C109: 663.01 | D109: 713.14 | E109: 607.91 | F109: 524.41 | G109: 576.89 | H109: 412.01
A111: ANALYSIS PART
...

Sheet Energy 
A1: RELIANCE INDUSTRIES (sa)
A2: Figures (In Crores) | C2: FY25 | D2: FY24 | E2: FY23 | F2: FY22 | G2: FY21 | H2: FY20
A3: Net Revenue from Operations | C3: 517349 | D3: 534534 | E3: 528315 | F3: 423703 | G3: 245667 | H3: 336953
A4: COGS | C4: 432209 | D4: 432598 | E4: 439391 | F4: 350736 | G4: 194548 | H4: 266135
A5: Current Assets | C5: 269563 | D5: 262625 | E5: 265932 | F5: 222398 | G5: 210719 | H5: 166654
A6: Inventory | C6: 89216 | D6: 85100 | E6: 48926 | F6: 45923 | G6: 37437 | H6: 38802
A7: Trade Receivables | C7: 15591 | D7: 14740 | E7: 16898 | F7: 14394 | G7: 4159 | H7: 7483
A8: Current Liability | C8: 257935 | D8: 240014 | E8: 237276 | F8: 200982 | G8: 201787 | H8: 330682
A9: Trade Payables | C9: 122379 | D9: 129859 | E9: 110722 | F9: 134005 | G9: 86999 | H9: 71048
A11: ANALYSIS PART
A12: WORKING CAPITAL | B12: CURRENT ASSETS - CURRENT LIABILITY | C12: =C5-C8 -> 11628 | D12: =D5-D8 -> 22611 | E12: =E5-E8 -> 28656 | F12: =F5-F8 -> 21416 | G12: =G5-G8 -> 8932 | H12: =H5-H8 -> -164028
A13: AVERAGE INVENTORY | B13: (Opening Inventory + Closing Inventory)/2 | C13: =(C6+D6)/2 -> 87158 | D13: =(D6+E6)/2 -> 67013 | E13: =(E6+F6)/2 -> 47424.5 | F13: =(F6+G6)/2 -> 41680 | G13: =(G6+H6)/2 -> 38119.5
A14: AVERAGE RECEIVABLES | B14: (Opening Receivables + Closing Receivables)/2 | C14: =(C7+D7)/2 -> 15165.5 | D14: =(D7+E7)/2 -> 15819 | E14: =(E7+F7)/2 -> 15646 | F14: =(F7+G7)/2 -> 9276.5 | G14: =(G7+H7)/2 -> 5821
A15: AVERAGE PAYABLES | B15: (Opening Payables + Closing Payables)/2 | C15: =(C9+D9)/2 -> 126119 | D15: =(D9+E9)/2 -> 120290.5 | E15: =(E9+F9)/2 -> 122363.5 | F15: =(F9+G9)/2 -> 110502 | G15: =(G9+H9)/2 -> 79023.5
A16: DAYS INVENTORY OUTSTANDING (DIO) (In Days) | B16: (Average Inventory / COGS)*365 | C16: =(C13/C4)*365 -> 73.60483 | D16: =(D13/D4)*365 -> 56.541512 | E16: =(E13/E4)*365 -> 39.395305 | F16: =(F13/F4)*365 -> 43.375074 | G16: =(G13/G4)*365 -> 71.517659
A17: DAYS SALES OUTSTANDING (DSO) (In Days) | B17: (Average Receivables / Revenue)*365 | C17: =(C14/C3)*365 -> 10.699562 | D17: =(D14/D3)*365 -> 10.801811 | E17: =(E14/E3)*365 -> 10.809441 | F17: =(F14/F3)*365 -> 7.9912639 | G17: =(G14/G3)*365 -> 8.6485568
A18: DAYS PAYABLE OUTSTANDING (DPO) (In Days) | B18: (Average Payables / COGS)*365 | C18: =(C15/C4)*365 -> 106.50735 | D18: =(D15/D4)*365 -> 101.49384 | E18: =(E15/E4)*365 -> 101.64677 | F18: =(F15/F4)*365 -> 114.99598 | G18: =(G15/G4)*365 -> 148.25944
A19: CASH CONVERSION CYCLE (CCC) (In Days) | B19: DIO + DSO - DPO | C19: =C16+C17-C18 -> -22.202958 | D19: =D16+D17-D18 -> -34.150518 | E19: =E16+E17-E18 -> -51.442027 | F19: =F16+F17-F18 -> -63.629642 | G19: =G16+G17-G18 -> -68.093224
A21: INDIAN OIL CORPORATION
A22: Figures (In Crores) | C22: FY25 | D22: FY24 | E22: FY23 | F22: FY22 | G22: FY21 | H22: FY20
A23: Net Revenue from Operations | C23: 758105.81 | D23: 776351.85 | E23: 841755.91 | F23: 589335.74 | G23: 363949.67 | H23: 483763.04
A24: COGS | C24: 656785.5 | D24: 638799.16 | E24: 747634.99 | F24: 486952.9 | G24: 275466.59 | H24: =281080+139463+5-5414.35 -> 415133.65
A25: Current Assets | C25: 157643.15 | D25: 158448.27 | E25: 158865.49 | F25: 146860.69 | G25: 116208.69 | H25: 110735.28
A26: Inventory | C26: 113878.49 | D26: 121375.83 | E26: 121107.58 | F26: 111736.51 | G26: 83427.46 | H26: 67010.76
A27: Trade Receivables | C27: 18550.96 | D27: 13831.45 | E27: 16271.21 | F27: 18700.42 | G27: 13800.2 | H27: 13259.48
A28: Current Liability | C28: 230614.41 | D28: 216403.93 | E28: 206658.33 | F28: 192154.7 | G28: 162174.89 | H28: 161517.84
A29: Trade Payables | C29: 60534.94 | D29: 59454.1 | E29: 54734.1 | F29: 49045.91 | G29: 37247.97 | H29: 27576.26
A31: ANALYSIS PART
A32: WORKING CAPITAL | B32: CURRENT ASSETS - CURRENT LIABILITY | C32: =C25-C28 -> -72971.26 | D32: =D25-D28 -> -57955.66 | E32: =E25-E28 -> -47792.84 | F32: =F25-F28 -> -45294.01 | G32: =G25-G28 -> -45966.2 | H32: =H25-H28 -> -50782.56
A33: AVERAGE INVENTORY | B33: (Opening Inventory + Closing Inventory)/2 | C33: =(C26+D26)/2 -> 117627.16 | D33: =(D26+E26)/2 -> 121241.71 | E33: =(E26+F26)/2 -> 116422.04 | F33: =(F26+G26)/2 -> 97581.985 | G33: =(G26+H26)/2 -> 75219.11
A34: AVERAGE RECEIVABLES | B34: (Opening Receivables + Closing Receivables)/2 | C34: =(C27+D27)/2 -> 16191.205 | D34: =(D27+E27)/2 -> 15051.33 | E34: =(E27+F27)/2 -> 17485.815 | F34: =(F27+G27)/2 -> 16250.31 | G34: =(G27+H27)/2 -> 13529.84
A35: AVERAGE PAYABLES | B35: (Opening Payables + Closing Payables)/2 | C35: =(C29+D29)/2 -> 59994.52 | D35: =(D29+E29)/2 -> 57094.1 | E35: =(E29+F29)/2 -> 51890.005 | F35: =(F29+G29)/2 -> 43146.94 | G35: =(G29+H29)/2 -> 32412.115
A36: DAYS INVENTORY OUTSTANDING (DIO) (In Days) | B36: (Average Inventory / COGS)*365 | C36: =(C33/C24)*365 -> 65.369764 | D36: =(D33/D24)*365 -> 69.275643 | E36: =(E33/E24)*365 -> 56.837958 | F36: =(F33/F24)*365 -> 73.143469 | G36: =(G33/G24)*365 -> 99.667169
A37: DAYS SALES OUTSTANDING (DSO) (In Days) | B37: (Average Receivables / Revenue)*365 | C37: =(C34/C23)*365 -> 7.7954683 | D37: =(D34/D23)*365 -> 7.0763475 | E37: =(E34/E23)*365 -> 7.5821534 | F37: =(F34/F23)*365 -> 10.064489 | G37: =(G34/G23)*365 -> 13.568886
A38: DAYS PAYABLE OUTSTANDING (DPO) (In Days) | B38: (Average Payables / COGS)*365 | C38: =(C35/C24)*365 -> 33.341174 | D38: =(D35/D24)*365 -> 32.622689 | E38: =(E35/E24)*365 -> 25.33302 | F38: =(F35/F24)*365 -> 32.341184 | G38: =(G35/G24)*365 -> 42.946849
A39: CASH CONVERSION CYCLE (CCC) (In Days) | B39: DIO + DSO - DPO | C39: =C36+C37-C38 -> 39.824058 | D39: =D36+D37-D38 -> 43.729301 | E39: =E36+E37-E38 -> 39.087092 | F39: =F36+F37-F38 -> 50.866775 | G39: =G36+G37-G38 -> 70.289206
A41: Bharat Petroleum Corporation
A42: Figures (In Crores) | C42: FY25 | D42: FY24 | E42: FY23 | F42: FY22 | G42: FY21 | H42: FY20
A43: Net Revenue from Operations | C43: 440271.86 | D43: 448083.03 | E43: 473187.18 | F43: 346791.12 | G43: 230162.63 | H43: 284571.9
A44: COGS | C44: 385296.91 | D44: 376096.15 | E44: 433212.29 | F44: 303401.27 | G44: 187398.76 | H44: 252592.13
A45: Current Assets | C45: 72832.22 | D45: 65694.11 | E45: 56012.93 | F45: 61999.36 | G45: 51982.49 | H45: 43251.75
A46: Inventory | C46: 45265.19 | D46: 42836.13 | E46: 38069.19 | F46: 42178.74 | G46: 26706.02 | H46: 22242.6
A47: Trade Receivables | C47: 9338.98 | D47: 8342.03 | E47: 6723.78 | F47: 9707.47 | G47: 7834.77 | H47: 5378.02
A48: Current Liability | C48: 90672 | D48: 80883.38 | E48: 74841.71 | F48: 83068.47 | G48: 56930.38 | H48: 60221.5
A49: Trade Payables | C49: 30634.06 | D49: 28305.81 | E49: 24024.26 | F49: 30347.72 | G49: 16262.67 | H49: 13107.21
A51: ANALYSIS PART
A52: WORKING CAPITAL | B52: CURRENT ASSETS - CURRENT LIABILITY | C52: =C45-C48 -> -17839.78 | D52: =D45-D48 -> -15189.27 | E52: =E45-E48 -> -18828.78 | F52: =F45-F48 -> -21069.11 | G52: =G45-G48 -> -4947.89 | H52: =H45-H48 -> -16969.75
A53: AVERAGE INVENTORY | B53: (Opening Inventory + Closing Inventory)/2 | C53: =(C46+D46)/2 -> 44050.66 | D53: =(D46+E46)/2 -> 40452.66 | E53: =(E46+F46)/2 -> 40123.965 | F53: =(F46+G46)/2 -> 34442.38 | G53: =(G46+H46)/2 -> 24474.31
A54: AVERAGE RECEIVABLES | B54: (Opening Receivables + Closing Receivables)/2 | C54: =(C47+D47)/2 -> 8840.505 | D54: =(D47+E47)/2 -> 7532.905 | E54: =(E47+F47)/2 -> 8215.625 | F54: =(F47+G47)/2 -> 8771.12 | G54: =(G47+H47)/2 -> 6606.395
A55: AVERAGE PAYABLES | B55: (Opening Payables + Closing Payables)/2 | C55: =(C49+D49)/2 -> 29469.935 | D55: =(D49+E49)/2 -> 26165.035 | E55: =(E49+F49)/2 -> 27185.99 | F55: =(F49+G49)/2 -> 23305.195 | G55: =(G49+H49)/2 -> 14684.94
A56: DAYS INVENTORY OUTSTANDING (DIO) (In Days) | B56: (Average Inventory / COGS)*365 | C56: =(C53/C44)*365 -> 41.730132 | D56: =(D53/D44)*365 -> 39.259165 | E56: =(E53/E44)*365 -> 33.806167 | F56: =(F53/F44)*365 -> 41.435122 | G56: =(G53/G44)*365 -> 47.669062
A57: DAYS SALES OUTSTANDING (DSO) (In Days) | B57: (Average Receivables / Revenue)*365 | C57: =(C54/C43)*365 -> 7.3290724 | D57: =(D54/D43)*365 -> 6.1361626 | E57: =(E54/E43)*365 -> 6.3372451 | F57: =(F54/F43)*365 -> 9.2316631 | G57: =(G54/G43)*365 -> 10.476654
A58: DAYS PAYABLE OUTSTANDING (DPO) (In Days) | B58: (Average Payables / COGS)*365 | C58: =(C55/C44)*365 -> 27.917499 | D58: =(D55/D44)*365 -> 25.393075 | E58: =(E55/E44)*365 -> 22.905367 | F58: =(F55/F44)*365 -> 28.036785 | G58: =(G55/G44)*365 -> 28.602127
A59: CASH CONVERSION CYCLE (CCC) (In Days) | B59: DIO + DSO - DPO | C59: =C56+C57-C58 -> 21.141705 | D59: =D56+D57-D58 -> 20.002253 | E59: =E56+E57-E58 -> 17.238046 | F59: =F56+F57-F58 -> 22.63 | G59: =G56+G57-G58 -> 29.543589
A61: ONGC
A62: Figures (In Crores) | C62: FY25 | D62: FY24 | E62: FY23 | F62: FY22 | G62: FY21 | H62: FY20
A63: Net Revenue from Operations | C63: 612065.37 | D63: 591447.12 | E63: 632325.97 | F63: 491269.8 | G63: 304000.98 | H63: 396762.57
A64: COGS | C64: 477885.73 | D64: 490963.07 | E64: 471049.36 | F64: 342535.77 | G64: 203567.72 | H64: 279504.95
A65: Current Assets | C65: 134796.54 | D65: 133341.03 | E65: 114150.53 | F65: 106059.3 | G65: 93184.16 | H65: 80709.45
A66: Inventory | C66: 58956.33 | D66: 52250.51 | E66: 44238.07 | F66: 54163.1 | G66: 44573.33 | H66: 33051.2
A67: Trade Receivables | C67: 21227.8 | D67: 19762.95 | E67: 18751.58 | F67: 19187.28 | G67: 16015.83 | H67: 9173.41
A68: Current Liability | C68: 166842.01 | D68: 151277.46 | E68: 132270.18 | F68: 127424.28 | G68: 123264.75 | H68: 125072.58
A69: Trade Payables | C69: 38975.53 | D69: 37490.29 | E69: 33642.6 | F69: 40171.07 | G69: 27449.15 | H69: 22961.13
A71: ANALYSIS PART
A72: WORKING CAPITAL | B72: CURRENT ASSETS - CURRENT LIABILITY | C72: =C65-C68 -> -32045.47 | D72: =D65-D68 -> -17936.43 | E72: =E65-E68 -> -18119.65 | F72: =F65-F68 -> -21364.98 | G72: =G65-G68 -> -30080.59 | H72: =H65-H68 -> -44363.13
A73: AVERAGE INVENTORY | B73: (Opening Inventory + Closing Inventory)/2 | C73: =(C66+D66)/2 -> 55603.42 | D73: =(D66+E66)/2 -> 48244.29 | E73: =(E66+F66)/2 -> 49200.585 | F73: =(F66+G66)/2 -> 49368.215 | G73: =(G66+H66)/2 -> 38812.265
A74: AVERAGE RECEIVABLES | B74: (Opening Receivables + Closing Receivables)/2 | C74: =(C67+D67)/2 -> 20495.375 | D74: =(D67+E67)/2 -> 19257.265 | E74: =(E67+F67)/2 -> 18969.43 | F74: =(F67+G67)/2 -> 17601.555 | G74: =(G67+H67)/2 -> 12594.62
A75: AVERAGE PAYABLES | B75: (Opening Payables + Closing Payables)/2 | C75: =(C69+D69)/2 -> 38232.91 | D75: =(D69+E69)/2 -> 35566.445 | E75: =(E69+F69)/2 -> 36906.835 | F75: =(F69+G69)/2 -> 33810.11 | G75: =(G69+H69)/2 -> 25205.14
A76: DAYS INVENTORY OUTSTANDING (DIO) (In Days) | B76: (Average Inventory / COGS)*365 | C76: =(C73/C64)*365 -> 42.468831 | D76: =(D73/D64)*365 -> 35.866579 | E76: =(E73/E64)*365 -> 38.123847 | F76: =(F73/F64)*365 -> 52.605888 | G76: =(G73/G64)*365 -> 69.590978
A77: DAYS SALES OUTSTANDING (DSO) (In Days) | B77: (Average Receivables / Revenue)*365 | C77: =(C74/C63)*365 -> 12.222243 | D77: =(D74/D63)*365 -> 11.884244 | E77: =(E74/E63)*365 -> 10.949798 | F77: =(F74/F63)*365 -> 13.077473 | G77: =(G74/G63)*365 -> 15.121781
A78: DAYS PAYABLE OUTSTANDING (DPO) (In Days) | B78: (Average Payables / COGS)*365 | C78: =(C75/C64)*365 -> 29.201567 | D78: =(D75/D64)*365 -> 26.441403 | E78: =(E75/E64)*365 -> 28.597841 | F78: =(F75/F64)*365 -> 36.027449 | G78: =(G75/G64)*365 -> 45.193197
A79: CASH CONVERSION CYCLE (CCC) (In Days) | B79: DIO + DSO - DPO | C79: =C76+C77-C78 -> 25.489507 | D79: =D76+D77-D78 -> 21.30942 | E79: =E76+E77-E78 -> 20.475804 | F79: =F76+F77-F78 -> 29.655912 | G79: =G76+G77-G78 -> 39.519562
A81: GAIL
A82: Figures (In Crores) | C82: FY25 | D82: FY24 | E82: FY23 | F82: FY22 | G82: FY21 | H82: FY20
A83: Net Revenue from Operations | C83: 141903.49 | D83: 133228.46 | E83: 145668.3 | F83: 92769.83 | G83: 57371.91 | H83: 72517.7
A84: COGS | C84: 115738.22 | D84: 107954.52 | E84: 128831.33 | F84: 70107.18 | G84: 43725.21 | H84: 56862.11
A85: Current Assets | C85: 21501.7 | D85: 20271.81 | E85: 20530.69 | F85: 16307.15 | G85: 10867.23 | H85: 11994.43
A86: Inventory | C86: 6249.92 | D86: 5970 | E86: 5917.92 | F86: 3576.61 | G86: 2989.73 | H86: 3183.01
A87: Trade Receivables | C87: 9436.44 | D87: 9580.27 | E87: 10679.61 | F87: 7446.53 | G87: 3501.5 | H87: 4818.31
A88: Current Liability | C88: 21899.51 | D88: 21640.54 | E88: 21711.02 | F88: 15092.73 | G88: 12552.33 | H88: 12476.15
A89: Trade Payables | C89: 7759.85 | D89: 6639.67 | E89: 7143.56 | F89: 5361.26 | G89: 4453.18 | H89: 3922.18
A91: ANALYSIS PART
A92: WORKING CAPITAL | B92: CURRENT ASSETS - CURRENT LIABILITY | C92: =C85-C88 -> -397.81 | D92: =D85-D88 -> -1368.73 | E92: =E85-E88 -> -1180.33 | F92: =F85-F88 -> 1214.42 | G92: =G85-G88 -> -1685.1 | H92: =H85-H88 -> -481.72
A93: AVERAGE INVENTORY | B93: (Opening Inventory + Closing Inventory)/2 | C93: =(C86+D86)/2 -> 6109.96 | D93: =(D86+E86)/2 -> 5943.96 | E93: =(E86+F86)/2 -> 4747.265 | F93: =(F86+G86)/2 -> 3283.17 | G93: =(G86+H86)/2 -> 3086.37
A94: AVERAGE RECEIVABLES | B94: (Opening Receivables + Closing Receivables)/2 | C94: =(C87+D87)/2 -> 9508.355 | D94: =(D87+E87)/2 -> 10129.94 | E94: =(E87+F87)/2 -> 9063.07 | F94: =(F87+G87)/2 -> 5474.015 | G94: =(G87+H87)/2 -> 4159.905
A95: AVERAGE PAYABLES | B95: (Opening Payables + Closing Payables)/2 | C95: =(C89+D89)/2 -> 7199.76 | D95: =(D89+E89)/2 -> 6891.615 | E95: =(E89+F89)/2 -> 6252.41 | F95: =(F89+G89)/2 -> 4907.22 | G95: =(G89+H89)/2 -> 4187.68
A96: DAYS INVENTORY OUTSTANDING (DIO) (In Days) | B96: (Average Inventory / COGS)*365 | C96: =(C93/C84)*365 -> 19.26879 | D96: =(D93/D84)*365 -> 20.096846 | E96: =(E93/E84)*365 -> 13.44977 | F96: =(F93/F84)*365 -> 17.093214 | G96: =(G93/G84)*365 -> 25.763742
A97: DAYS SALES OUTSTANDING (DSO) (In Days) | B97: (Average Receivables / Revenue)*365 | C97: =(C94/C83)*365 -> 24.457112 | D97: =(D94/D83)*365 -> 27.75254 | E97: =(E94/E83)*365 -> 22.709269 | F97: =(F94/F83)*365 -> 21.537341 | G97: =(G94/G83)*365 -> 26.465309
A98: DAYS PAYABLE OUTSTANDING (DPO) (In Days) | B98: (Average Payables / COGS)*365 | C98: =(C95/C84)*365 -> 22.705658 | D98: =(D95/D84)*365 -> 23.300919 | E98: =(E95/E84)*365 -> 17.714089 | F98: =(F95/F84)*365 -> 25.548529 | G98: =(G95/G84)*365 -> 34.957024
A99: CASH CONVERSION CYCLE (CCC) (In Days) | B99: DIO + DSO - DPO | C99: =C96+C97-C98 -> 21.020244 | D99: =D96+D97-D98 -> 24.548467 | E99: =E96+E97-E98 -> 18.444949 | F99: =F96+F97-F98 -> 13.082027 | G99: =G96+G97-G98 -> 17.272028
A101: Petronet LNG
A102: Figures (In Crores) | C102: FY25 | D102: FY24 | E102: FY23 | F102: FY22 | G102: FY21 | H102: FY20
A103: Net Revenue from Operations | C103: 50982.03 | D103: 52729.33 | E103: 59899.35 | F103: 43168.57 | G103: 26022.9 | H103: 35452
A104: COGS | C104: 44297.87 | D104: 46464.11 | E104: 53952.35 | F104: 37077.47 | G104: 20681.5 | H104: 30495.94
A105: Current Assets | C105: 15202.59 | D105: 12894.1 | E105: 11846.97 | F105: 8715.32 | G105: 8161.8 | H105: 7048.82
A106: Inventory | C106: 1204.42 | D106: 1465.44 | E106: 1153.05 | F106: 576.68 | G106: 337.18 | H106: 480.89
A107: Trade Receivables | C107: 3266.89 | D107: 3626.08 | E107: 3839.7 | F107: 2684.44 | G107: 1874.53 | H107: 1602.57
A108: Current Liability | C108: 4060.1 | D108: 4158.2 | E108: 2900.4 | F108: 2736.74 | G108: 2074.44 | H108: 2423.61
A109: Trade Payables | C109: 2563.04 | D109: 2864.95 | E109: 1644.39 | F109: 1526.83 | G109: 1035.45 | H109: 1166.07
A111: ANALYSIS PART
...

Sheet Metals
A1: HINDALCO INDUSTRIES
A2: Figures (In Crores) | C2: FY25 | D2: FY24 | E2: FY23 | F2: FY22 | G2: FY21 | H2: FY20
A3: Net Revenue from Operations | C3: 238496 | D3: 215962 | E3: 223202 | F3: 195059 | G3: 131985 | H3: 118144
A4: COGS | C4: 159345 | D4: 148331 | E4: 158116 | F4: 128686 | G4: 85228 | H4: =77727+256-17 -> 77966
A5: Current Assets | C5: 101959 | D5: 82343 | E5: 89311 | F5: 98543 | G5: 67628 | H5: 66282
A6: Inventory | C6: 48801 | D6: 40812 | E6: 42958 | F6: 44483 | G6: 30668 | H6: 22384
A7: Trade Receivables | C7: 19834 | D7: 16404 | E7: 16214 | F7: 21076 | G7: 12959 | H7: 9345
A8: Current Liability | C8: 65516 | D8: 59351 | E8: 60457 | F8: 77273 | G8: 48493 | H8: 37217
A9: Trade Payables | C9: 40632 | D9: 34444 | E9: 35860 | F9: 41382 | G9: 28280 | H9: 18300
A11: ANALYSIS PART
A12: WORKING CAPITAL | B12: CURRENT ASSETS - CURRENT LIABILITY | C12: =C5-C8 -> 36443 | D12: =D5-D8 -> 22992 | E12: =E5-E8 -> 28854 | F12: =F5-F8 -> 21270 | G12: =G5-G8 -> 19135 | H12: =H5-H8 -> 29065
A13: AVERAGE INVENTORY | B13: (Opening Inventory + Closing Inventory)/2 | C13: =(C6+D6)/2 -> 44806.5 | D13: =(D6+E6)/2 -> 41885 | E13: =(E6+F6)/2 -> 43720.5 | F13: =(F6+G6)/2 -> 37575.5 | G13: =(G6+H6)/2 -> 26526
A14: AVERAGE RECEIVABLES | B14: (Opening Receivables + Closing Receivables)/2 | C14: =(C7+D7)/2 -> 18119 | D14: =(D7+E7)/2 -> 16309 | E14: =(E7+F7)/2 -> 18645 | F14: =(F7+G7)/2 -> 17017.5 | G14: =(G7+H7)/2 -> 11152
A15: AVERAGE PAYABLES | B15: (Opening Payables + Closing Payables)/2 | C15: =(C9+D9)/2 -> 37538 | D15: =(D9+E9)/2 -> 35152 | E15: =(E9+F9)/2 -> 38621 | F15: =(F9+G9)/2 -> 34831 | G15: =(G9+H9)/2 -> 23290
A16: DAYS INVENTORY OUTSTANDING (DIO) (In Days) | B16: (Average Inventory / COGS)*365 | C16: =(C13/C4)*365 -> 102.63499 | D16: =(D13/D4)*365 -> 103.06696 | E16: =(E13/E4)*365 -> 100.92579 | F16: =(F13/F4)*365 -> 106.5777 | G16: =(G13/G4)*365 -> 113.60105
A17: DAYS SALES OUTSTANDING (DSO) (In Days) | B17: (Average Receivables / Revenue)*365 | C17: =(C14/C3)*365 -> 27.729752 | D17: =(D14/D3)*365 -> 27.564039 | E17: =(E14/E3)*365 -> 30.489982 | F17: =(F14/F3)*365 -> 31.843634 | G17: =(G14/G3)*365 -> 30.840474
A18: DAYS PAYABLE OUTSTANDING (DPO) (In Days) | B18: (Average Payables / COGS)*365 | C18: =(C15/C4)*365 -> 85.985566 | D18: =(D15/D4)*365 -> 86.498979 | E18: =(E15/E4)*365 -> 89.153944 | F18: =(F15/F4)*365 -> 98.793303 | G18: =(G15/G4)*365 -> 99.742456
A19: CASH CONVERSION CYCLE (CCC) (In Days) | B19: DIO + DSO - DPO | C19: =C16+C17-C18 -> 44.379176 | D19: =D16+D17-D18 -> 44.132019 | E19: =E16+E17-E18 -> 42.26183 | F19: =F16+F17-F18 -> 39.628028 | G19: =G16+G17-G18 -> 44.699065
A21: TATA STEEL LTD
A22: Figures (In Crores) | C22: FY25 | D22: FY24 | E22: FY23 | F22: FY22 | G22: FY21 | H22: FY20
A23: Net Revenue from Operations | C23: 218542.51 | D23: 229170.78 | E23: 243352.69 | F23: 243959.17 | G23: 156477.4 | H23: 148971.71
A24: COGS | C24: 95000.65 | D24: 101915.74 | E24: 113238.3 | F24: 83478.74 | G24: 56617.58 | H24: 64587.08
A25: Current Assets | C25: 68391.54 | D25: 70548.24 | E25: 86665.54 | F25: 92556.61 | G25: 60211.9 | H25: 58732.72
A26: Inventory | C26: 44589.94 | D26: 49157.51 | E26: 54415.33 | F26: 48824.39 | G26: 33276.38 | H26: 31068.72
A27: Trade Receivables | C27: 5260.06 | D27: 6263.53 | E27: 8257.24 | F27: 12246.43 | G27: 9539.84 | H27: 7884.91
A28: Current Liability | C28: 86093.55 | D28: 98403.48 | E28: 97295.13 | F28: 90588 | G28: 70867.1 | H28: 61660.91
A29: Trade Payables | C29: 29314.38 | D29: 35434.66 | E29: 37832.54 | F29: 36764.87 | G29: 25967.49 | H29: 21380.85
A31: ANALYSIS PART
A32: WORKING CAPITAL | B32: CURRENT ASSETS - CURRENT LIABILITY | C32: =C25-C28 -> -17702.01 | D32: =D25-D28 -> -27855.24 | E32: =E25-E28 -> -10629.59 | F32: =F25-F28 -> 1968.61 | G32: =G25-G28 -> -10655.2 | H32: =H25-H28 -> -2928.19
A33: AVERAGE INVENTORY | B33: (Opening Inventory + Closing Inventory)/2 | C33: =(C26+D26)/2 -> 46873.725 | D33: =(D26+E26)/2 -> 51786.42 | E33: =(E26+F26)/2 -> 51619.86 | F33: =(F26+G26)/2 -> 41050.385 | G33: =(G26+H26)/2 -> 32172.55
A34: AVERAGE RECEIVABLES | B34: (Opening Receivables + Closing Receivables)/2 | C34: =(C27+D27)/2 -> 5761.795 | D34: =(D27+E27)/2 -> 7260.385 | E34: =(E27+F27)/2 -> 10251.835 | F34: =(F27+G27)/2 -> 10893.135 | G34: =(G27+H27)/2 -> 8712.375
A35: AVERAGE PAYABLES | B35: (Opening Payables + Closing Payables)/2 | C35: =(C29+D29)/2 -> 32374.52 | D35: =(D29+E29)/2 -> 36633.6 | E35: =(E29+F29)/2 -> 37298.705 | F35: =(F29+G29)/2 -> 31366.18 | G35: =(G29+H29)/2 -> 23674.17
A36: DAYS INVENTORY OUTSTANDING (DIO) (In Days) | B36: (Average Inventory / COGS)*365 | C36: =(C33/C24)*365 -> 180.09255 | D36: =(D33/D24)*365 -> 185.46736 | E36: =(E33/E24)*365 -> 166.38583 | F36: =(F33/F24)*365 -> 179.4875 | G36: =(G33/G24)*365 -> 207.40874
A37: DAYS SALES OUTSTANDING (DSO) (In Days) | B37: (Average Receivables / Revenue)*365 | C37: =(C34/C23)*365 -> 9.6230943 | D37: =(D34/D23)*365 -> 11.563606 | E37: =(E34/E23)*365 -> 15.376529 | F37: =(F34/F23)*365 -> 16.297786 | G37: =(G34/G23)*365 -> 20.322531
A38: DAYS PAYABLE OUTSTANDING (DPO) (In Days) | B38: (Average Payables / COGS)*365 | C38: =(C35/C24)*365 -> 124.38546 | D38: =(D35/D24)*365 -> 131.1992 | E38: =(E35/E24)*365 -> 120.22458 | F38: =(F35/F24)*365 -> 137.14457 | G38: =(G35/G24)*365 -> 152.62171
A39: CASH CONVERSION CYCLE (CCC) (In Days) | B39: DIO + DSO - DPO | C39: =C36+C37-C38 -> 65.330185 | D39: =D36+D37-D38 -> 65.831762 | E39: =E36+E37-E38 -> 61.53778 | F39: =F36+F37-F38 -> 58.64072 | G39: =G36+G37-G38 -> 75.109555
A41: JSW STEEL
A42: Figures (In Crores) | C42: FY25 | D42: FY24 | E42: FY23 | F42: FY22 | G42: FY21 | H42: FY20
A43: Net Revenue from Operations | C43: 168824 | D43: 175006 | E43: 165960 | F43: 146371 | G43: 79839 | H43: 73326
A44: COGS | C44: 99142 | D44: 101678 | E44: 93334 | F44: 59270 | G44: 32508 | H44: 38730
A45: Current Assets | C45: 70736 | D45: 64534 | E45: 68150 | F45: 65374 | G45: 35852 | H45: 36478
A46: Inventory | C46: 34956 | D46: 37815 | E46: 33135 | F46: 33787 | G46: 14249 | H46: 13773
A47: Trade Receivables | C47: 8415 | D47: 7548 | E47: 7134 | F47: 7457 | G47: 4486 | H47: 4505
A48: Current Liability | C48: 60626 | D48: 66065 | E48: 69963 | F48: 57551 | G48: 43299 | H48: 43688
A49: Trade Payables | C49: 12018 | D49: 33365 | E49: 38203 | F49: 30889 | G49: 15243 | H49: 17918
A51: ANALYSIS PART
A52: WORKING CAPITAL | B52: CURRENT ASSETS - CURRENT LIABILITY | C52: =C45-C48 -> 10110 | D52: =D45-D48 -> -1531 | E52: =E45-E48 -> -1813 | F52: =F45-F48 -> 7823 | G52: =G45-G48 -> -7447 | H52: =H45-H48 -> -7210
A53: AVERAGE INVENTORY | B53: (Opening Inventory + Closing Inventory)/2 | C53: =(C46+D46)/2 -> 36385.5 | D53: =(D46+E46)/2 -> 35475 | E53: =(E46+F46)/2 -> 33461 | F53: =(F46+G46)/2 -> 24018 | G53: =(G46+H46)/2 -> 14011
A54: AVERAGE RECEIVABLES | B54: (Opening Receivables + Closing Receivables)/2 | C54: =(C47+D47)/2 -> 7981.5 | D54: =(D47+E47)/2 -> 7341 | E54: =(E47+F47)/2 -> 7295.5 | F54: =(F47+G47)/2 -> 5971.5 | G54: =(G47+H47)/2 -> 4495.5
A55: AVERAGE PAYABLES | B55: (Opening Payables + Closing Payables)/2 | C55: =(C49+D49)/2 -> 22691.5 | D55: =(D49+E49)/2 -> 35784 | E55: =(E49+F49)/2 -> 34546 | F55: =(F49+G49)/2 -> 23066 | G55: =(G49+H49)/2 -> 16580.5
A56: DAYS INVENTORY OUTSTANDING (DIO) (In Days) | B56: (Average Inventory / COGS)*365 | C56: =(C53/C44)*365 -> 133.95642 | D56: =(D53/D44)*365 -> 127.34687 | E56: =(E53/E44)*365 -> 130.85548 | F56: =(F53/F44)*365 -> 147.90906 | G56: =(G53/G44)*365 -> 157.31558
A57: DAYS SALES OUTSTANDING (DSO) (In Days) | B57: (Average Receivables / Revenue)*365 | C57: =(C54/C43)*365 -> 17.256122 | D57: =(D54/D43)*365 -> 15.310704 | E57: =(E54/E43)*365 -> 16.045177 | F57: =(F54/F43)*365 -> 14.890911 | G57: =(G54/G43)*365 -> 20.55208
A58: DAYS PAYABLE OUTSTANDING (DPO) (In Days) | B58: (Average Payables / COGS)*365 | C58: =(C55/C44)*365 -> 83.540755 | D58: =(D55/D44)*365 -> 128.45611 | E58: =(E55/E44)*365 -> 135.09857 | F58: =(F55/F44)*365 -> 142.0464 | G58: =(G55/G44)*365 -> 186.16594
A59: CASH CONVERSION CYCLE (CCC) (In Days) | B59: DIO + DSO - DPO | C59: =C56+C57-C58 -> 67.671788 | D59: =D56+D57-D58 -> 14.201467 | E59: =E56+E57-E58 -> 11.802082 | F59: =F56+F57-F58 -> 20.753573 | G59: =G56+G57-G58 -> -8.2982801
A61: VEDANTA LTD
A62: Figures (In Crores) | C62: FY25 | D62: FY24 | E62: FY23 | F62: FY22 | G62: FY21 | H62: FY20
A63: Net Revenue from Operations | C63: 152968 | D63: 143727 | E63: 147308 | F63: 132732 | G63: 88021 | H63: 84447
A64: COGS | C64: 49022 | D64: 44407 | E64: 44150 | F64: 56420 | G64: 37356 | H64: 39109
A65: Current Assets | C65: 51765 | D65: 51924 | E65: 60507 | F65: 68575 | G65: 56192 | H65: 57520
A66: Inventory | C66: 14474 | D66: 13001 | E66: 15012 | F66: 14313 | G66: 9923 | H66: 11335
A67: Trade Receivables | C67: 3636 | D67: 3607 | E67: 4014 | F67: 4946 | G67: 3491 | H67: 2697
A68: Current Liability | C68: 73575 | D68: 78661 | E68: 88026 | F68: 65713 | G68: 59124 | H68: 63322
A69: Trade Payables | C69: 10195 | D69: 10095 | E69: 11043 | F69: 21531 | G69: 7892 | H69: 8027
A71: ANALYSIS PART
A72: WORKING CAPITAL | B72: CURRENT ASSETS - CURRENT LIABILITY | C72: =C65-C68 -> -21810 | D72: =D65-D68 -> -26737 | E72: =E65-E68 -> -27519 | F72: =F65-F68 -> 2862 | G72: =G65-G68 -> -2932 | H72: =H65-H68 -> -5802
A73: AVERAGE INVENTORY | B73: (Opening Inventory + Closing Inventory)/2 | C73: =(C66+D66)/2 -> 13737.5 | D73: =(D66+E66)/2 -> 14006.5 | E73: =(E66+F66)/2 -> 14662.5 | F73: =(F66+G66)/2 -> 12118 | G73: =(G66+H66)/2 -> 10629
A74: AVERAGE RECEIVABLES | B74: (Opening Receivables + Closing Receivables)/2 | C74: =(C67+D67)/2 -> 3621.5 | D74: =(D67+E67)/2 -> 3810.5 | E74: =(E67+F67)/2 -> 4480 | F74: =(F67+G67)/2 -> 4218.5 | G74: =(G67+H67)/2 -> 3094
A75: AVERAGE PAYABLES | B75: (Opening Payables + Closing Payables)/2 | C75: =(C69+D69)/2 -> 10145 | D75: =(D69+E69)/2 -> 10569 | E75: =(E69+F69)/2 -> 16287 | F75: =(F69+G69)/2 -> 14711.5 | G75: =(G69+H69)/2 -> 7959.5
A76: DAYS INVENTORY OUTSTANDING (DIO) (In Days) | B76: (Average Inventory / COGS)*365 | C76: =(C73/C64)*365 -> 102.28443 | D76: =(D73/D64)*365 -> 115.12537 | E76: =(E73/E64)*365 -> 121.21886 | F76: =(F73/F64)*365 -> 78.395427 | G76: =(G73/G64)*365 -> 103.8544
A77: DAYS SALES OUTSTANDING (DSO) (In Days) | B77: (Average Receivables / Revenue)*365 | C77: =(C74/C63)*365 -> 8.6413335 | D77: =(D74/D63)*365 -> 9.6769048 | E77: =(E74/E63)*365 -> 11.100551 | F77: =(F74/F63)*365 -> 11.600462 | G77: =(G74/G63)*365 -> 12.830006
A78: DAYS PAYABLE OUTSTANDING (DPO) (In Days) | B78: (Average Payables / COGS)*365 | C78: =(C75/C64)*365 -> 75.535984 | D78: =(D75/D64)*365 -> 86.871101 | E78: =(E75/E64)*365 -> 134.64904 | F78: =(F75/F64)*365 -> 95.173653 | G78: =(G75/G64)*365 -> 77.771108
A79: CASH CONVERSION CYCLE (CCC) (In Days) | B79: DIO + DSO - DPO | C79: =C76+C77-C78 -> 35.389783 | D79: =D76+D77-D78 -> 37.931178 | E79: =E76+E77-E78 -> -2.32963 | F79: =F76+F77-F78 -> -5.177764 | G79: =G76+G77-G78 -> 38.9133
A81: STEEL AUTHORITY OF INDIA
A82: Figures (In Crores) | C82: FY25 | D82: FY24 | E82: FY23 | F82: FY22 | G82: FY21 | H82: FY20
A83: Net Revenue from Operations | C83: 102479.06 | D83: 105378.33 | E83: 104447.72 | F83: 103476.84 | G83: 69113.61 | H83: 61664.16
A84: COGS | C84: 50997.19 | D84: 54354.49 | E84: 57025.2 | F84: 42610.58 | G84: 27490.23 | H84: =29371.73-5577.63 -> 23794.1
A85: Current Assets | C85: 46480.36 | D85: 52762.98 | E85: 42629.91 | F85: 33445.89 | G85: 36420.47 | H85: 41125.46
A86: Inventory | C86: 33743.33 | D86: 37346.74 | E86: 32400.19 | F86: 24166.73 | G86: 19570.43 | H86: 23836.27
A87: Trade Receivables | C87: 7609.94 | D87: 8355.37 | E87: 5389.97 | F87: 4770.85 | G87: 7153.7 | H87: 8844.73
A88: Current Liability | C88: 46190.09 | D88: 53464.42 | E88: 49334.28 | F88: 39342.92 | G88: 46497.63 | H88: 44964.84
A89: Trade Payables | C89: 10503.99 | D89: 15332.39 | E89: 14341.7 | F89: 16921.83 | G89: 7015 | H89: 6322.37
A91: ANALYSIS PART
A92: WORKING CAPITAL | B92: CURRENT ASSETS - CURRENT LIABILITY | C92: =C85-C88 -> 290.27 | D92: =D85-D88 -> -701.44 | E92: =E85-E88 -> -6704.37 | F92: =F85-F88 -> -5897.03 | G92: =G85-G88 -> -10077.16 | H92: =H85-H88 -> -3839.38
A93: AVERAGE INVENTORY | B93: (Opening Inventory + Closing Inventory)/2 | C93: =(C86+D86)/2 -> 35545.035 | D93: =(D86+E86)/2 -> 34873.465 | E93: =(E86+F86)/2 -> 28283.46 | F93: =(F86+G86)/2 -> 21868.58 | G93: =(G86+H86)/2 -> 21703.35
A94: AVERAGE RECEIVABLES | B94: (Opening Receivables + Closing Receivables)/2 | C94: =(C87+D87)/2 -> 7982.655 | D94: =(D87+E87)/2 -> 6872.67 | E94: =(E87+F87)/2 -> 5080.41 | F94: =(F87+G87)/2 -> 5962.275 | G94: =(G87+H87)/2 -> 7999.215
A95: AVERAGE PAYABLES | B95: (Opening Payables + Closing Payables)/2 | C95: =(C89+D89)/2 -> 12918.19 | D95: =(D89+E89)/2 -> 14837.045 | E95: =(E89+F89)/2 -> 15631.765 | F95: =(F89+G89)/2 -> 11968.415 | G95: =(G89+H89)/2 -> 6668.685
A96: DAYS INVENTORY OUTSTANDING (DIO) (In Days) | B96: (Average Inventory / COGS)*365 | C96: =(C93/C84)*365 -> 254.40495 | D96: =(D93/D84)*365 -> 234.18148 | E96: =(E93/E84)*365 -> 181.03335 | F96: =(F93/F84)*365 -> 187.32511 | G96: =(G93/G84)*365 -> 288.16502
A97: DAYS SALES OUTSTANDING (DSO) (In Days) | B97: (Average Receivables / Revenue)*365 | C97: =(C94/C83)*365 -> 28.431848 | D97: =(D94/D83)*365 -> 23.804937 | E97: =(E94/E83)*365 -> 17.753855 | F97: =(F94/F83)*365 -> 21.031087 | G97: =(G94/G83)*365 -> 42.245131
A98: DAYS PAYABLE OUTSTANDING (DPO) (In Days) | B98: (Average Payables / COGS)*365 | C98: =(C95/C84)*365 -> 92.458807 | D98: =(D95/D84)*365 -> 99.633378 | E98: =(E95/E84)*365 -> 100.05391 | F98: =(F95/F84)*365 -> 102.52082 | G98: =(G95/G84)*365 -> 88.543094
A99: CASH CONVERSION CYCLE (CCC) (In Days) | B99: DIO + DSO - DPO | C99: =C96+C97-C98 -> 190.378 | D99: =D96+D97-D98 -> 158.35304 | E99: =E96+E97-E98 -> 98.733293 | F99: =F96+F97-F98 -> 105.83538 | G99: =G96+G97-G98 -> 241.86706
A101: GODAWARI POWER AND ISPAT LTD
A102: Figures (In Crores) | C102: FY25 | D102: FY24 | E102: FY23 | F102: FY22 | G102: FY21 | H102: FY20
A103: Net Revenue from Operations | C103: 5375.73 | D103: 5455.35 | E103: 5753.04 | F103: 5399.18 | G103: 4071.92 | H103: 3288.53
A104: COGS | C104: 3110.57 | D104: 3091.31 | E104: 3481.83 | F104: 2391.71 | G104: 1847.6 | H104: =1681.49+88.08+44.91 -> 1814.48
A105: Current Assets | C105: 2267.01 | D105: 2406.7 | E105: 2322.75 | F105: 2381.05 | G105: 1027.83 | H105: 933.2
A106: Inventory | C106: 931.82 | D106: 900.31 | E106: 810.79 | F106: 873.63 | G106: 503.67 | H106: 557.4
A107: Trade Receivables | C107: 132.34 | D107: 211.94 | E107: 295.74 | F107: 349.92 | G107: 275.23 | H107: 176.78
A108: Current Liability | C108: 938.06 | D108: 745.21 | E108: 947.65 | F108: 1235.04 | G108: 409.43 | H108: 453.98
A109: Trade Payables | C109: 459.94 | D109: 529.19 | E109: 524.48 | F109: 529.6 | G109: 196.19 | H109: 178.25
A111: ANALYSIS PART
...

Sheet Pharma
A1: SUN PHARMACEUTICALS INDUSTRIES
A2: Figures (In Crores) | C2: FY25 | D2: FY24 | E2: FY23 | F2: FY22 | G2: FY21 | H2: FY20
A3: Net Revenue from Operations | C3: 52578.44 | D3: 48496.85 | E3: 43885.68 | F3: 38654.49 | G3: 33498.14 | H3: 32325.17
A4: COGS | C4: 10747.36 | D4: 11292.87 | E4: 11223.48 | F4: 10909.35 | G4: 8690.08 | H4: 9230.45
A5: Current Assets | C5: 52624.47 | D5: 43474.98 | E5: 39883.34 | F5: 35014.98 | G5: 30442.08 | H5: 31654.16
A6: Inventory | C6: 10243.33 | D6: 9868.29 | E6: 10513.05 | F6: 8996.81 | G6: 8997.02 | H6: 7874.99
A7: Trade Receivables | C7: 13046.11 | D7: 11249.37 | E7: 11438.51 | F7: 10592.89 | G7: 9061.4 | H7: 9421.24
A8: Current Liability | C8: 18194.21 | D8: 16984.4 | E8: 19907 | F8: 17200.55 | G8: 16145.63 | H8: 15706.43
A9: Trade Payables | C9: 6184.34 | D9: 5653.3 | E9: 5681.52 | F9: 4479.34 | G9: 3973.66 | H9: 3583.64
A11: ANALYSIS PART
A12: WORKING CAPITAL | B12: CURRENT ASSETS - CURRENT LIABILITY | C12: =C5-C8 -> 34430.26 | D12: =D5-D8 -> 26490.58 | E12: =E5-E8 -> 19976.34 | F12: =F5-F8 -> 17814.43 | G12: =G5-G8 -> 14296.45 | H12: =H5-H8 -> 15947.73
A13: AVERAGE INVENTORY | B13: (Opening Inventory + Closing Inventory)/2 | C13: =(C6+D6)/2 -> 10055.81 | D13: =(D6+E6)/2 -> 10190.67 | E13: =(E6+F6)/2 -> 9754.93 | F13: =(F6+G6)/2 -> 8996.915 | G13: =(G6+H6)/2 -> 8436.005
A14: AVERAGE RECEIVABLES | B14: (Opening Receivables + Closing Receivables)/2 | C14: =(C7+D7)/2 -> 12147.74 | D14: =(D7+E7)/2 -> 11343.94 | E14: =(E7+F7)/2 -> 11015.7 | F14: =(F7+G7)/2 -> 9827.145 | G14: =(G7+H7)/2 -> 9241.32
A15: AVERAGE PAYABLES | B15: (Opening Payables + Closing Payables)/2 | C15: =(C9+D9)/2 -> 5918.82 | D15: =(D9+E9)/2 -> 5667.41 | E15: =(E9+F9)/2 -> 5080.43 | F15: =(F9+G9)/2 -> 4226.5 | G15: =(G9+H9)/2 -> 3778.65
A16: DAYS INVENTORY OUTSTANDING (DIO) (In Days) | B16: (Average Inventory / COGS)*365 | C16: =(C13/C4)*365 -> 341.5137 | D16: =(D13/D4)*365 -> 329.37549 | E16: =(E13/E4)*365 -> 317.24113 | F16: =(F13/F4)*365 -> 301.01463 | G16: =(G13/G4)*365 -> 354.32836
A17: DAYS SALES OUTSTANDING (DSO) (In Days) | B17: (Average Receivables / Revenue)*365 | C17: =(C14/C3)*365 -> 84.32972 | D17: =(D14/D3)*365 -> 85.377465 | E17: =(E14/E3)*365 -> 91.61828 | F17: =(F14/F3)*365 -> 92.794082 | G17: =(G14/G3)*365 -> 100.6946
A18: DAYS PAYABLE OUTSTANDING (DPO) (In Days) | B18: (Average Payables / COGS)*365 | C18: =(C15/C4)*365 -> 201.01395 | D18: =(D15/D4)*365 -> 183.17794 | E18: =(E15/E4)*365 -> 165.22121 | F18: =(F15/F4)*365 -> 141.40829 | G18: =(G15/G4)*365 -> 158.71054
A19: CASH CONVERSION CYCLE (CCC) (In Days) | B19: DIO + DSO - DPO | C19: =C16+C17-C18 -> 224.82947 | D19: =D16+D17-D18 -> 231.57501 | E19: =E16+E17-E18 -> 243.6382 | F19: =F16+F17-F18 -> 252.40043 | G19: =G16+G17-G18 -> 296.31243
A21: DR REDDY'S LABORATORIES
A22: Figures (In Crores) | C22: FY25 | D22: FY24 | E22: FY23 | F22: FY22 | G22: FY21 | H22: FY20
A23: Net Revenue from Operations | C23: 32643.9 | D23: 28011.1 | E23: 24669.7 | F23: 21545.2 | G23: 19047.5 | H23: 17517
A24: COGS | C24: 9979.9 | D24: 8208.7 | E24: 7657.7 | F24: 7442.2 | G24: 6078.9 | H24: 5554.4
A25: Current Assets | C25: 25018.1 | D25: 24805.3 | E25: 20425.5 | F25: 17782.3 | G25: 14550.3 | H25: 12599.1
A26: Inventory | C26: 7108.5 | D26: 6355.2 | E26: 4867 | F26: 5088.4 | G26: 4541.2 | H26: 3506.7
A27: Trade Receivables | C27: 9042 | D27: 8029.8 | E27: 7248.5 | F27: 6676.4 | G27: 4964.1 | H27: 5027.8
A28: Current Liability | C28: 13033.8 | D28: 9588 | E28: 8572.1 | F28: 9765.8 | G28: 8103.8 | H28: 7214.1
A29: Trade Payables | C29: 2647.8 | D29: 2614.4 | E29: 2268.4 | F29: 2266.2 | G29: 1810.9 | H29: 1524.8
A31: ANALYSIS PART
A32: WORKING CAPITAL | B32: CURRENT ASSETS - CURRENT LIABILITY | C32: =C25-C28 -> 11984.3 | D32: =D25-D28 -> 15217.3 | E32: =E25-E28 -> 11853.4 | F32: =F25-F28 -> 8016.5 | G32: =G25-G28 -> 6446.5 | H32: =H25-H28 -> 5385
A33: AVERAGE INVENTORY | B33: (Opening Inventory + Closing Inventory)/2 | C33: =(C26+D26)/2 -> 6731.85 | D33: =(D26+E26)/2 -> 5611.1 | E33: =(E26+F26)/2 -> 4977.7 | F33: =(F26+G26)/2 -> 4814.8 | G33: =(G26+H26)/2 -> 4023.95
A34: AVERAGE RECEIVABLES | B34: (Opening Receivables + Closing Receivables)/2 | C34: =(C27+D27)/2 -> 8535.9 | D34: =(D27+E27)/2 -> 7639.15 | E34: =(E27+F27)/2 -> 6962.45 | F34: =(F27+G27)/2 -> 5820.25 | G34: =(G27+H27)/2 -> 4995.95
A35: AVERAGE PAYABLES | B35: (Opening Payables + Closing Payables)/2 | C35: =(C29+D29)/2 -> 2631.1 | D35: =(D29+E29)/2 -> 2441.4 | E35: =(E29+F29)/2 -> 2267.3 | F35: =(F29+G29)/2 -> 2038.55 | G35: =(G29+H29)/2 -> 1667.85
A36: DAYS INVENTORY OUTSTANDING (DIO) (In Days) | B36: (Average Inventory / COGS)*365 | C36: =(C33/C24)*365 -> 246.2074 | D36: =(D33/D24)*365 -> 249.49767 | E36: =(E33/E24)*365 -> 237.25929 | F36: =(F33/F24)*365 -> 236.14012 | G36: =(G33/G24)*365 -> 241.61308
A37: DAYS SALES OUTSTANDING (DSO) (In Days) | B37: (Average Receivables / Revenue)*365 | C37: =(C34/C23)*365 -> 95.442135 | D37: =(D34/D23)*365 -> 99.542315 | E37: =(E34/E23)*365 -> 103.01277 | F37: =(F34/F23)*365 -> 98.601603 | G37: =(G34/G23)*365 -> 95.73549
A38: DAYS PAYABLE OUTSTANDING (DPO) (In Days) | B38: (Average Payables / COGS)*365 | C38: =(C35/C24)*365 -> 96.228569 | D38: =(D35/D24)*365 -> 108.5569 | E38: =(E35/E24)*365 -> 108.06959 | F38: =(F35/F24)*365 -> 99.979945 | G38: =(G35/G24)*365 -> 100.14398
A39: CASH CONVERSION CYCLE (CCC) (In Days) | B39: DIO + DSO - DPO | C39: =C36+C37-C38 -> 245.42097 | D39: =D36+D37-D38 -> 240.48309 | E39: =E36+E37-E38 -> 232.20248 | F39: =F36+F37-F38 -> 234.76178 | G39: =G36+G37-G38 -> 237.20459
A41: AUROBINDO PHARMA
A42: Figures (In Crores) | C42: FY25 | D42: FY24 | E42: FY23 | F42: FY22 | G42: FY21 | H42: FY20
A43: Net Revenue from Operations | C43: 31723.73 | D43: 29001.87 | E43: 24855.38 | F43: 23455.49 | G43: 24774.62 | H43: 23098.51
A44: COGS | C44: 13026.24 | D44: 12602.9 | E44: 11293.26 | F44: 10140.28 | G44: 9902.47 | H44: 9735.23
A45: Current Assets | C45: 27162.46 | D45: 24205.63 | E45: 21545.67 | F45: 18122.69 | G45: 19823.51 | H45: 16412.5
A46: Inventory | C46: 10543.72 | D46: 9808.23 | E46: 8511.23 | F46: 7553.85 | G46: 9026.57 | H46: 7699.87
A47: Trade Receivables | C47: 5745.93 | D47: 4816.74 | E47: 4466.38 | F47: 4012.26 | G47: 3503.28 | H47: 4315.15
A48: Current Liability | C48: 14682.34 | D48: 12199.13 | E48: 11493.78 | F48: 8155.98 | G48: 10665.15 | H48: 11386.75
A49: Trade Payables | C49: 4188.85 | D49: 4454.16 | E49: 3871.31 | F49: 2703.05 | G49: 2794.68 | H49: 2545.01
A51: ANALYSIS PART
A52: WORKING CAPITAL | B52: CURRENT ASSETS - CURRENT LIABILITY | C52: =C45-C48 -> 12480.12 | D52: =D45-D48 -> 12006.5 | E52: =E45-E48 -> 10051.89 | F52: =F45-F48 -> 9966.71 | G52: =G45-G48 -> 9158.36 | H52: =H45-H48 -> 5025.75
A53: AVERAGE INVENTORY | B53: (Opening Inventory + Closing Inventory)/2 | C53: =(C46+D46)/2 -> 10175.975 | D53: =(D46+E46)/2 -> 9159.73 | E53: =(E46+F46)/2 -> 8032.54 | F53: =(F46+G46)/2 -> 8290.21 | G53: =(G46+H46)/2 -> 8363.22
A54: AVERAGE RECEIVABLES | B54: (Opening Receivables + Closing Receivables)/2 | C54: =(C47+D47)/2 -> 5281.335 | D54: =(D47+E47)/2 -> 4641.56 | E54: =(E47+F47)/2 -> 4239.32 | F54: =(F47+G47)/2 -> 3757.77 | G54: =(G47+H47)/2 -> 3909.215
A55: AVERAGE PAYABLES | B55: (Opening Payables + Closing Payables)/2 | C55: =(C49+D49)/2 -> 4321.505 | D55: =(D49+E49)/2 -> 4162.735 | E55: =(E49+F49)/2 -> 3287.18 | F55: =(F49+G49)/2 -> 2748.865 | G55: =(G49+H49)/2 -> 2669.845
A56: DAYS INVENTORY OUTSTANDING (DIO) (In Days) | B56: (Average Inventory / COGS)*365 | C56: =(C53/C44)*365 -> 285.13453 | D56: =(D53/D44)*365 -> 265.28033 | E56: =(E53/E44)*365 -> 259.613 | F56: =(F53/F44)*365 -> 298.40662 | G56: =(G53/G44)*365 -> 308.26403
A57: DAYS SALES OUTSTANDING (DSO) (In Days) | B57: (Average Receivables / Revenue)*365 | C57: =(C54/C43)*365 -> 60.764837 | D57: =(D54/D43)*365 -> 58.415868 | E57: =(E54/E43)*365 -> 62.2542 | F57: =(F54/F43)*365 -> 58.47612 | G57: =(G54/G43)*365 -> 57.593758
A58: DAYS PAYABLE OUTSTANDING (DPO) (In Days) | B58: (Average Payables / COGS)*365 | C58: =(C55/C44)*365 -> 121.09015 | D58: =(D55/D44)*365 -> 120.55942 | E58: =(E55/E44)*365 -> 106.24219 | F58: =(F55/F44)*365 -> 98.945564 | G58: =(G55/G44)*365 -> 98.409127
A59: CASH CONVERSION CYCLE (CCC) (In Days) | B59: DIO + DSO - DPO | C59: =C56+C57-C58 -> 224.80922 | D59: =D56+D57-D58 -> 203.13678 | E59: =E56+E57-E58 -> 215.62501 | F59: =F56+F57-F58 -> 257.93717 | G59: =G56+G57-G58 -> 267.44866
A61: CIPLA
A62: Figures (In Crores) | C62: FY25 | D62: FY24 | E62: FY23 | F62: FY22 | G62: FY21 | H62: FY20
A63: Net Revenue from Operations | C63: 27547.62 | D63: 25774.09 | E63: 22753.12 | F63: 21763.34 | G63: 19159.59 | H63: 17131.99
A64: COGS | C64: 9596.71 | D64: 9460.19 | E64: 8252.28 | F64: 8495.6 | G64: 7351.89 | H64: 5991.42
A65: Current Assets | C65: 23288.52 | D65: 19441.41 | E65: 17274.95 | F65: 14727.54 | G65: 13209.51 | H65: 11706.18
A66: Inventory | C66: 5642.11 | D66: 5237.95 | E66: 5156.43 | F66: 5350.24 | G66: 4669.18 | H66: 4377.6
A67: Trade Receivables | C67: 5506.37 | D67: 4770.66 | E67: 4057 | F67: 3424.44 | G67: 3445.68 | H67: 3891.31
A68: Current Liability | C68: 5483.96 | D68: 5245.77 | E68: 5109.67 | F68: 4913.21 | G68: 4591.55 | H68: 4393.14
A69: Trade Payables | C69: 2837.49 | D69: 2473.98 | E69: 2457.05 | F69: 2508.1 | G69: 2066.82 | H69: 2281.81
A71: ANALYSIS PART
A72: WORKING CAPITAL | B72: CURRENT ASSETS - CURRENT LIABILITY | C72: =C65-C68 -> 17804.56 | D72: =D65-D68 -> 14195.64 | E72: =E65-E68 -> 12165.28 | F72: =F65-F68 -> 9814.33 | G72: =G65-G68 -> 8617.96 | H72: =H65-H68 -> 7313.04
A73: AVERAGE INVENTORY | B73: (Opening Inventory + Closing Inventory)/2 | C73: =(C66+D66)/2 -> 5440.03 | D73: =(D66+E66)/2 -> 5197.19 | E73: =(E66+F66)/2 -> 5253.335 | F73: =(F66+G66)/2 -> 5009.71 | G73: =(G66+H66)/2 -> 4523.39
A74: AVERAGE RECEIVABLES | B74: (Opening Receivables + Closing Receivables)/2 | C74: =(C67+D67)/2 -> 5138.515 | D74: =(D67+E67)/2 -> 4413.83 | E74: =(E67+F67)/2 -> 3740.72 | F74: =(F67+G67)/2 -> 3435.06 | G74: =(G67+H67)/2 -> 3668.495
A75: AVERAGE PAYABLES | B75: (Opening Payables + Closing Payables)/2 | C75: =(C69+D69)/2 -> 2655.735 | D75: =(D69+E69)/2 -> 2465.515 | E75: =(E69+F69)/2 -> 2482.575 | F75: =(F69+G69)/2 -> 2287.46 | G75: =(G69+H69)/2 -> 2174.315
A76: DAYS INVENTORY OUTSTANDING (DIO) (In Days) | B76: (Average Inventory / COGS)*365 | C76: =(C73/C64)*365 -> 206.90538 | D76: =(D73/D64)*365 -> 200.5218 | E76: =(E73/E64)*365 -> 232.35606 | F76: =(F73/F64)*365 -> 215.23426 | G76: =(G73/G64)*365 -> 224.57318
A77: DAYS SALES OUTSTANDING (DSO) (In Days) | B77: (Average Receivables / Revenue)*365 | C77: =(C74/C63)*365 -> 68.084211 | D77: =(D74/D63)*365 -> 62.506492 | E77: =(E74/E63)*365 -> 60.007718 | F77: =(F74/F63)*365 -> 57.6105 | G77: =(G74/G63)*365 -> 69.886708
A78: DAYS PAYABLE OUTSTANDING (DPO) (In Days) | B78: (Average Payables / COGS)*365 | C78: =(C75/C64)*365 -> 101.00787 | D78: =(D75/D64)*365 -> 95.126311 | E78: =(E75/E64)*365 -> 109.80479 | F78: =(F75/F64)*365 -> 98.277096 | G78: =(G75/G64)*365 -> 107.94843
A79: CASH CONVERSION CYCLE (CCC) (In Days) | B79: DIO + DSO - DPO | C79: =C76+C77-C78 -> 173.98172 | D79: =D76+D77-D78 -> 167.90198 | E79: =E76+E77-E78 -> 182.55899 | F79: =F76+F77-F78 -> 174.56766 | G79: =G76+G77-G78 -> 186.51146
A81: ZYDUS LIFESCIENCES
A82: Figures (In Crores) | C82: FY25 | D82: FY24 | E82: FY23 | F82: FY22 | G82: FY21 | H82: FY20
A83: Net Revenue from Operations | C83: 23241.5 | D83: 19547.4 | E83: 17237.4 | F83: 15265.2 | G83: 14403.5 | H83: 14253.1
A84: COGS | C84: 6338 | D84: 6228.2 | E84: 6310.1 | F84: 5545.2 | G84: 4802.1 | H84: 4920
A85: Current Assets | C85: 17046.1 | D85: 11501.4 | E85: 10016.4 | F85: 12261.4 | G85: 8716 | H85: 8715.4
A86: Inventory | C86: 3944 | D86: 3441.9 | E86: 3413.3 | F86: 3719.4 | G86: 3236.2 | H86: 2789
A87: Trade Receivables | C87: 4024.7 | D87: 5220.2 | E87: 4416.8 | F87: 3340.3 | G87: 3127.3 | H87: 3663.2
A88: Current Liability | C88: 9041.6 | D88: 5341.9 | E88: 5530.7 | F88: 7839.4 | G88: 7861.3 | H88: 8269.4
A89: Trade Payables | C89: 2305.8 | D89: 2126.7 | E89: 2125 | F89: 2137.8 | G89: 2205.9 | H89: 2044.3
A91: ANALYSIS PART
A92: WORKING CAPITAL | B92: CURRENT ASSETS - CURRENT LIABILITY | C92: =C85-C88 -> 8004.5 | D92: =D85-D88 -> 6159.5 | E92: =E85-E88 -> 4485.7 | F92: =F85-F88 -> 4422 | G92: =G85-G88 -> 854.7 | H92: =H85-H88 -> 446
A93: AVERAGE INVENTORY | B93: (Opening Inventory + Closing Inventory)/2 | C93: =(C86+D86)/2 -> 3692.95 | D93: =(D86+E86)/2 -> 3427.6 | E93: =(E86+F86)/2 -> 3566.35 | F93: =(F86+G86)/2 -> 3477.8 | G93: =(G86+H86)/2 -> 3012.6
A94: AVERAGE RECEIVABLES | B94: (Opening Receivables + Closing Receivables)/2 | C94: =(C87+D87)/2 -> 4622.45 | D94: =(D87+E87)/2 -> 4818.5 | E94: =(E87+F87)/2 -> 3878.55 | F94: =(F87+G87)/2 -> 3233.8 | G94: =(G87+H87)/2 -> 3395.25
A95: AVERAGE PAYABLES | B95: (Opening Payables + Closing Payables)/2 | C95: =(C89+D89)/2 -> 2216.25 | D95: =(D89+E89)/2 -> 2125.85 | E95: =(E89+F89)/2 -> 2131.4 | F95: =(F89+G89)/2 -> 2171.85 | G95: =(G89+H89)/2 -> 2125.1
A96: DAYS INVENTORY OUTSTANDING (DIO) (In Days) | B96: (Average Inventory / COGS)*365 | C96: =(C93/C84)*365 -> 212.67383 | D96: =(D93/D84)*365 -> 200.87248 | E96: =(E93/E84)*365 -> 206.29114 | F96: =(F93/F84)*365 -> 228.91816 | G96: =(G93/G84)*365 -> 228.98294
A97: DAYS SALES OUTSTANDING (DSO) (In Days) | B97: (Average Receivables / Revenue)*365 | C97: =(C94/C83)*365 -> 72.594034 | D97: =(D94/D83)*365 -> 89.973731 | E97: =(E94/E83)*365 -> 82.127859 | F97: =(F94/F83)*365 -> 77.322079 | G97: =(G94/G83)*365 -> 86.039244
A98: DAYS PAYABLE OUTSTANDING (DPO) (In Days) | B98: (Average Payables / COGS)*365 | C98: =(C95/C84)*365 -> 127.63194 | D98: =(D95/D84)*365 -> 124.58419 | E98: =(E95/E84)*365 -> 123.28822 | F98: =(F95/F84)*365 -> 142.95702 | G98: =(G95/G84)*365 -> 161.52548
A99: CASH CONVERSION CYCLE (CCC) (In Days) | B99: DIO + DSO - DPO | C99: =C96+C97-C98 -> 157.63592 | D99: =D96+D97-D98 -> 166.26202 | E99: =E96+E97-E98 -> 165.13078 | F99: =F96+F97-F98 -> 163.28323 | G99: =G96+G97-G98 -> 153.49671
A101: ABBOTT INDIA LTD
A102: Figures (In Crores) | C102: FY25 | D102: FY24 | E102: FY23 | F102: FY22 | G102: FY21 | H102: FY20
A103: Net Revenue from Operations | C103: 6409.15 | D103: 5848.91 | E103: 5348.73 | F103: 4919.27 | G103: 4310.02 | H103: 4093.14
A104: COGS | C104: 3496.78 | D104: 3220.61 | E104: 2975.06 | F104: 2657.21 | G104: 2390.92 | H104: 2315.65
A105: Current Assets | C105: 4765.11 | D105: 3245.84 | E105: 3025.11 | F105: 3853.04 | G105: 3518.52 | H105: 3204.64
A106: Inventory | C106: 882.04 | D106: 619.58 | E106: 648.85 | F106: 687.82 | G106: 717.59 | H106: 527.17
A107: Trade Receivables | C107: 380.23 | D107: 319.11 | E107: 316.95 | F107: 288.16 | G107: 250.21 | H107: 317.91
A108: Current Liability | C108: 1407.19 | D108: 1342.72 | E108: 1206.02 | F108: 1203.19 | G108: 1030.86 | H108: 891.1
A109: Trade Payables | C109: 1057.86 | D109: 1002.69 | E109: 891.99 | F109: 889.45 | G109: 762.6 | H109: 657.77
A111: ANALYSIS PART
...
